{
  "duration": 499.05999755859375,
  "language": "german",
  "text": "Auf, auf, ihr Frauen! Richtig so, rasch ger\u00fcstet, Fertig, wurtig und flink. Und frei folgen, Sollt' ich sagen, Von Held Tristan, meinem Herrn. Vom Mast der Freude flacke, Sie wie Herr Lustig ins Lanz, In Markes B\u00fchne geschlossen, Macht sie ihr Anbekannt. Ruhm, Frau Polpet, ereilen! Ihr Staat zieht zu bereiten, Dass wir sie nicht gleiten. In Tristan bringe meinen Brust, Und meld' ihm, was ich sage. Sollt' ich zur Seite ihm gehen, Vor K\u00f6nig Marke zu stehen, Nicht m\u00f6cht' es nach Zucht und Wut geschehen, Empfing ich sie n\u00e4mlich zuvor F\u00fcr ungesinnte Schuld. Drum suche meine Huld, Da Marke wohl, und meld' es gut. Nicht woll' ich mich bereite, Ans Land ihn zu begleite, Nicht will' ich zur Seite ihm gehen, Vor K\u00f6nig Marke zu stehen, Wie geht er vergessen, Unvergeben nach Zucht, Und wogen ich zuvor F\u00fcr ungeb\u00fc\u00dfte Schuld. Wie bl\u00fcht ihm meine Huld? Nicht bewisst, was sag' ich ihm? Notbart, wie er mich h\u00f6rt. Anna, Frau von G\u00e4de, gr\u00fc\u00dfe mir dein, Gr\u00fc\u00dfe mir Vater und Mutter. Was ist? Was denkst du? Wolltest du fliehen? Wohin soll ich dir folgen? Bl\u00fchtest du nicht? Hier bleib' ich. Tristan, will' ich erwarten, Betreube, folg', was ich befehle, Den S\u00fcdeltrank r\u00fcspe schnell, Du wei\u00dft, den ich dir wies. Und welchen Trank? Welcher Trank? In die goldene Schale gie\u00df' er aus, Gef\u00fcllt fasst sie ihn ganz. Kennst du der Mutter K\u00fcnste nicht? Denkst du, die alles klug erweckt? Ohne Rat im Fremdes Land H\u00e4tt' sie mit Wehe mich entsandt. Wehe und Wunden gab sie wahrsam, F\u00fcr b\u00f6se Gifte jeden gibt. Der tiefstes Weh, Der h\u00f6chstes Leid Gab sie den Todestrank. Ihr Tod nun sag' ihr Dank, Ihr Tod nun sag' ihr Dank. Oh tiefstes Weh, Oh tiefstes Weh, H\u00f6rst du mir nach? Oh h\u00f6chstes Leid, Oh h\u00f6chstes Leid, Bist du betroffen?  Ja, Tristan! Ja, Tristan! Herr Tristan, Herr Tristan,          r",
  "words": [
    {
      "end": 0.7200000286102295,
      "start": 0.0,
      "word": "Auf"
    },
    {
      "end": 2.259999990463257,
      "start": 1.9199999570846558,
      "word": "auf"
    },
    {
      "end": 2.7799999713897705,
      "start": 2.640000104904175,
      "word": "ihr"
    },
    {
      "end": 5.239999771118164,
      "start": 2.7799999713897705,
      "word": "Frauen"
    },
    {
      "end": 9.479999542236328,
      "start": 8.720000267028809,
      "word": "Richtig"
    },
    {
      "end": 10.0,
      "start": 9.479999542236328,
      "word": "so"
    },
    {
      "end": 10.5,
      "start": 10.020000457763672,
      "word": "rasch"
    },
    {
      "end": 11.239999771118164,
      "start": 10.5,
      "word": "ger\u00fcstet"
    },
    {
      "end": 11.739999771118164,
      "start": 11.479999542236328,
      "word": "Fertig"
    },
    {
      "end": 12.199999809265137,
      "start": 12.119999885559082,
      "word": "wurtig"
    },
    {
      "end": 12.399999618530273,
      "start": 12.199999809265137,
      "word": "und"
    },
    {
      "end": 13.020000457763672,
      "start": 12.399999618530273,
      "word": "flink"
    },
    {
      "end": 15.800000190734863,
      "start": 15.479999542236328,
      "word": "Und"
    },
    {
      "end": 16.719999313354492,
      "start": 15.800000190734863,
      "word": "frei"
    },
    {
      "end": 17.920000076293945,
      "start": 16.719999313354492,
      "word": "folgen"
    },
    {
      "end": 19.260000228881836,
      "start": 18.219999313354492,
      "word": "Sollt"
    },
    {
      "end": 19.479999542236328,
      "start": 19.260000228881836,
      "word": "ich"
    },
    {
      "end": 20.200000762939453,
      "start": 19.479999542236328,
      "word": "sagen"
    },
    {
      "end": 20.760000228881836,
      "start": 20.520000457763672,
      "word": "Von"
    },
    {
      "end": 21.579999923706055,
      "start": 20.760000228881836,
      "word": "Held"
    },
    {
      "end": 22.719999313354492,
      "start": 21.579999923706055,
      "word": "Tristan"
    },
    {
      "end": 24.239999771118164,
      "start": 23.139999389648438,
      "word": "meinem"
    },
    {
      "end": 24.940000534057617,
      "start": 24.239999771118164,
      "word": "Herrn"
    },
    {
      "end": 26.860000610351562,
      "start": 25.940000534057617,
      "word": "Vom"
    },
    {
      "end": 27.520000457763672,
      "start": 26.860000610351562,
      "word": "Mast"
    },
    {
      "end": 27.920000076293945,
      "start": 27.520000457763672,
      "word": "der"
    },
    {
      "end": 29.1200008392334,
      "start": 27.920000076293945,
      "word": "Freude"
    },
    {
      "end": 30.360000610351562,
      "start": 29.1200008392334,
      "word": "flacke"
    },
    {
      "end": 31.6200008392334,
      "start": 30.979999542236328,
      "word": "Sie"
    },
    {
      "end": 32.060001373291016,
      "start": 31.6200008392334,
      "word": "wie"
    },
    {
      "end": 32.7599983215332,
      "start": 32.060001373291016,
      "word": "Herr"
    },
    {
      "end": 33.65999984741211,
      "start": 32.7599983215332,
      "word": "Lustig"
    },
    {
      "end": 33.91999816894531,
      "start": 33.65999984741211,
      "word": "ins"
    },
    {
      "end": 34.619998931884766,
      "start": 33.91999816894531,
      "word": "Lanz"
    },
    {
      "end": 36.29999923706055,
      "start": 35.65999984741211,
      "word": "In"
    },
    {
      "end": 37.5,
      "start": 36.29999923706055,
      "word": "Markes"
    },
    {
      "end": 38.2599983215332,
      "start": 37.5,
      "word": "B\u00fchne"
    },
    {
      "end": 40.279998779296875,
      "start": 38.2599983215332,
      "word": "geschlossen"
    },
    {
      "end": 41.20000076293945,
      "start": 40.70000076293945,
      "word": "Macht"
    },
    {
      "end": 41.779998779296875,
      "start": 41.20000076293945,
      "word": "sie"
    },
    {
      "end": 42.119998931884766,
      "start": 41.779998779296875,
      "word": "ihr"
    },
    {
      "end": 42.939998626708984,
      "start": 42.119998931884766,
      "word": "Anbekannt"
    },
    {
      "end": 45.79999923706055,
      "start": 44.400001525878906,
      "word": "Ruhm"
    },
    {
      "end": 46.2400016784668,
      "start": 46.2400016784668,
      "word": "Frau"
    },
    {
      "end": 47.2400016784668,
      "start": 46.2400016784668,
      "word": "Polpet"
    },
    {
      "end": 48.619998931884766,
      "start": 48.279998779296875,
      "word": "ereilen"
    },
    {
      "end": 49.599998474121094,
      "start": 49.31999969482422,
      "word": "Ihr"
    },
    {
      "end": 50.81999969482422,
      "start": 49.599998474121094,
      "word": "Staat"
    },
    {
      "end": 51.47999954223633,
      "start": 50.81999969482422,
      "word": "zieht"
    },
    {
      "end": 52.18000030517578,
      "start": 51.47999954223633,
      "word": "zu"
    },
    {
      "end": 53.880001068115234,
      "start": 52.18000030517578,
      "word": "bereiten"
    },
    {
      "end": 54.619998931884766,
      "start": 54.5,
      "word": "Dass"
    },
    {
      "end": 55.47999954223633,
      "start": 54.619998931884766,
      "word": "wir"
    },
    {
      "end": 55.84000015258789,
      "start": 55.47999954223633,
      "word": "sie"
    },
    {
      "end": 56.63999938964844,
      "start": 55.84000015258789,
      "word": "nicht"
    },
    {
      "end": 58.34000015258789,
      "start": 56.63999938964844,
      "word": "gleiten"
    },
    {
      "end": 75.5199966430664,
      "start": 74.12000274658203,
      "word": "In"
    },
    {
      "end": 76.91999816894531,
      "start": 75.5199966430664,
      "word": "Tristan"
    },
    {
      "end": 79.12000274658203,
      "start": 76.91999816894531,
      "word": "bringe"
    },
    {
      "end": 80.27999877929688,
      "start": 79.12000274658203,
      "word": "meinen"
    },
    {
      "end": 81.91999816894531,
      "start": 80.27999877929688,
      "word": "Brust"
    },
    {
      "end": 83.5,
      "start": 83.26000213623047,
      "word": "Und"
    },
    {
      "end": 84.72000122070312,
      "start": 83.5,
      "word": "meld"
    },
    {
      "end": 85.33999633789062,
      "start": 85.33999633789062,
      "word": "ihm"
    },
    {
      "end": 85.73999786376953,
      "start": 85.73999786376953,
      "word": "was"
    },
    {
      "end": 86.0199966430664,
      "start": 85.73999786376953,
      "word": "ich"
    },
    {
      "end": 88.05999755859375,
      "start": 86.0199966430664,
      "word": "sage"
    },
    {
      "end": 92.69999694824219,
      "start": 91.30000305175781,
      "word": "Sollt"
    },
    {
      "end": 93.0199966430664,
      "start": 93.0199966430664,
      "word": "ich"
    },
    {
      "end": 93.27999877929688,
      "start": 93.0199966430664,
      "word": "zur"
    },
    {
      "end": 94.05999755859375,
      "start": 93.27999877929688,
      "word": "Seite"
    },
    {
      "end": 94.66000366210938,
      "start": 94.05999755859375,
      "word": "ihm"
    },
    {
      "end": 96.27999877929688,
      "start": 94.66000366210938,
      "word": "gehen"
    },
    {
      "end": 97.23999786376953,
      "start": 97.19999694824219,
      "word": "Vor"
    },
    {
      "end": 98.63999938964844,
      "start": 97.23999786376953,
      "word": "K\u00f6nig"
    },
    {
      "end": 99.41999816894531,
      "start": 98.63999938964844,
      "word": "Marke"
    },
    {
      "end": 99.87999725341797,
      "start": 99.41999816894531,
      "word": "zu"
    },
    {
      "end": 100.58000183105469,
      "start": 99.87999725341797,
      "word": "stehen"
    },
    {
      "end": 102.68000030517578,
      "start": 102.12000274658203,
      "word": "Nicht"
    },
    {
      "end": 103.44000244140625,
      "start": 102.68000030517578,
      "word": "m\u00f6cht"
    },
    {
      "end": 103.69999694824219,
      "start": 103.44000244140625,
      "word": "es"
    },
    {
      "end": 103.94000244140625,
      "start": 103.69999694824219,
      "word": "nach"
    },
    {
      "end": 104.86000061035156,
      "start": 103.94000244140625,
      "word": "Zucht"
    },
    {
      "end": 105.30000305175781,
      "start": 104.86000061035156,
      "word": "und"
    },
    {
      "end": 106.27999877929688,
      "start": 105.30000305175781,
      "word": "Wut"
    },
    {
      "end": 107.0199966430664,
      "start": 106.27999877929688,
      "word": "geschehen"
    },
    {
      "end": 108.91999816894531,
      "start": 108.0199966430664,
      "word": "Empfing"
    },
    {
      "end": 109.36000061035156,
      "start": 108.91999816894531,
      "word": "ich"
    },
    {
      "end": 109.77999877929688,
      "start": 109.36000061035156,
      "word": "sie"
    },
    {
      "end": 110.22000122070312,
      "start": 109.77999877929688,
      "word": "n\u00e4mlich"
    },
    {
      "end": 112.0199966430664,
      "start": 110.22000122070312,
      "word": "zuvor"
    },
    {
      "end": 113.5999984741211,
      "start": 112.0199966430664,
      "word": "F\u00fcr"
    },
    {
      "end": 116.23999786376953,
      "start": 113.5999984741211,
      "word": "ungesinnte"
    },
    {
      "end": 117.05999755859375,
      "start": 116.23999786376953,
      "word": "Schuld"
    },
    {
      "end": 122.19999694824219,
      "start": 120.80000305175781,
      "word": "Drum"
    },
    {
      "end": 123.5999984741211,
      "start": 122.19999694824219,
      "word": "suche"
    },
    {
      "end": 124.9000015258789,
      "start": 123.5999984741211,
      "word": "meine"
    },
    {
      "end": 126.54000091552734,
      "start": 124.9000015258789,
      "word": "Huld"
    },
    {
      "end": 129.9199981689453,
      "start": 128.8000030517578,
      "word": "Da"
    },
    {
      "end": 131.39999389648438,
      "start": 129.9199981689453,
      "word": "Marke"
    },
    {
      "end": 132.36000061035156,
      "start": 131.39999389648438,
      "word": "wohl"
    },
    {
      "end": 133.4600067138672,
      "start": 133.4600067138672,
      "word": "und"
    },
    {
      "end": 134.3800048828125,
      "start": 133.4600067138672,
      "word": "meld"
    },
    {
      "end": 134.89999389648438,
      "start": 134.3800048828125,
      "word": "es"
    },
    {
      "end": 135.60000610351562,
      "start": 134.89999389648438,
      "word": "gut"
    },
    {
      "end": 140.4199981689453,
      "start": 139.5,
      "word": "Nicht"
    },
    {
      "end": 141.0399932861328,
      "start": 140.4199981689453,
      "word": "woll"
    },
    {
      "end": 141.22000122070312,
      "start": 141.0399932861328,
      "word": "ich"
    },
    {
      "end": 141.4600067138672,
      "start": 141.22000122070312,
      "word": "mich"
    },
    {
      "end": 143.16000366210938,
      "start": 141.4600067138672,
      "word": "bereite"
    },
    {
      "end": 144.0399932861328,
      "start": 143.60000610351562,
      "word": "Ans"
    },
    {
      "end": 145.16000366210938,
      "start": 144.0399932861328,
      "word": "Land"
    },
    {
      "end": 145.74000549316406,
      "start": 145.16000366210938,
      "word": "ihn"
    },
    {
      "end": 146.1999969482422,
      "start": 145.74000549316406,
      "word": "zu"
    },
    {
      "end": 147.3000030517578,
      "start": 146.1999969482422,
      "word": "begleite"
    },
    {
      "end": 149.33999633789062,
      "start": 148.05999755859375,
      "word": "Nicht"
    },
    {
      "end": 150.32000732421875,
      "start": 149.33999633789062,
      "word": "will"
    },
    {
      "end": 150.72000122070312,
      "start": 150.72000122070312,
      "word": "ich"
    },
    {
      "end": 150.9600067138672,
      "start": 150.72000122070312,
      "word": "zur"
    },
    {
      "end": 151.74000549316406,
      "start": 150.9600067138672,
      "word": "Seite"
    },
    {
      "end": 152.47999572753906,
      "start": 151.74000549316406,
      "word": "ihm"
    },
    {
      "end": 153.86000061035156,
      "start": 152.47999572753906,
      "word": "gehen"
    },
    {
      "end": 154.83999633789062,
      "start": 154.67999267578125,
      "word": "Vor"
    },
    {
      "end": 156.27999877929688,
      "start": 154.83999633789062,
      "word": "K\u00f6nig"
    },
    {
      "end": 157.0,
      "start": 156.27999877929688,
      "word": "Marke"
    },
    {
      "end": 157.5,
      "start": 157.0,
      "word": "zu"
    },
    {
      "end": 159.0800018310547,
      "start": 157.5,
      "word": "stehen"
    },
    {
      "end": 160.47999572753906,
      "start": 160.0800018310547,
      "word": "Wie"
    },
    {
      "end": 161.1199951171875,
      "start": 160.47999572753906,
      "word": "geht"
    },
    {
      "end": 161.5,
      "start": 161.1199951171875,
      "word": "er"
    },
    {
      "end": 162.9600067138672,
      "start": 161.5,
      "word": "vergessen"
    },
    {
      "end": 164.8800048828125,
      "start": 163.9199981689453,
      "word": "Unvergeben"
    },
    {
      "end": 165.55999755859375,
      "start": 164.8800048828125,
      "word": "nach"
    },
    {
      "end": 166.44000244140625,
      "start": 165.55999755859375,
      "word": "Zucht"
    },
    {
      "end": 166.97999572753906,
      "start": 166.9199981689453,
      "word": "Und"
    },
    {
      "end": 167.55999755859375,
      "start": 166.97999572753906,
      "word": "wogen"
    },
    {
      "end": 167.97999572753906,
      "start": 167.55999755859375,
      "word": "ich"
    },
    {
      "end": 169.94000244140625,
      "start": 167.97999572753906,
      "word": "zuvor"
    },
    {
      "end": 171.67999267578125,
      "start": 169.94000244140625,
      "word": "F\u00fcr"
    },
    {
      "end": 174.4600067138672,
      "start": 171.67999267578125,
      "word": "ungeb\u00fc\u00dfte"
    },
    {
      "end": 176.02000427246094,
      "start": 174.4600067138672,
      "word": "Schuld"
    },
    {
      "end": 180.33999633789062,
      "start": 179.13999938964844,
      "word": "Wie"
    },
    {
      "end": 181.5399932861328,
      "start": 180.33999633789062,
      "word": "bl\u00fcht"
    },
    {
      "end": 182.39999389648438,
      "start": 181.5399932861328,
      "word": "ihm"
    },
    {
      "end": 183.0,
      "start": 182.39999389648438,
      "word": "meine"
    },
    {
      "end": 183.60000610351562,
      "start": 183.0,
      "word": "Huld"
    },
    {
      "end": 184.75999450683594,
      "start": 184.33999633789062,
      "word": "Nicht"
    },
    {
      "end": 185.47999572753906,
      "start": 184.75999450683594,
      "word": "bewisst"
    },
    {
      "end": 185.89999389648438,
      "start": 185.47999572753906,
      "word": "was"
    },
    {
      "end": 186.25999450683594,
      "start": 185.89999389648438,
      "word": "sag"
    },
    {
      "end": 186.39999389648438,
      "start": 186.25999450683594,
      "word": "ich"
    },
    {
      "end": 186.86000061035156,
      "start": 186.39999389648438,
      "word": "ihm"
    },
    {
      "end": 187.82000732421875,
      "start": 187.0800018310547,
      "word": "Notbart"
    },
    {
      "end": 188.5,
      "start": 188.24000549316406,
      "word": "wie"
    },
    {
      "end": 188.67999267578125,
      "start": 188.5,
      "word": "er"
    },
    {
      "end": 188.8800048828125,
      "start": 188.67999267578125,
      "word": "mich"
    },
    {
      "end": 189.47999572753906,
      "start": 188.8800048828125,
      "word": "h\u00f6rt"
    },
    {
      "end": 194.02000427246094,
      "start": 193.44000244140625,
      "word": "Anna"
    },
    {
      "end": 195.4600067138672,
      "start": 194.02000427246094,
      "word": "Frau"
    },
    {
      "end": 195.8800048828125,
      "start": 195.4600067138672,
      "word": "von"
    },
    {
      "end": 197.02000427246094,
      "start": 195.8800048828125,
      "word": "G\u00e4de"
    },
    {
      "end": 198.5399932861328,
      "start": 198.44000244140625,
      "word": "gr\u00fc\u00dfe"
    },
    {
      "end": 199.13999938964844,
      "start": 198.5399932861328,
      "word": "mir"
    },
    {
      "end": 200.47999572753906,
      "start": 199.13999938964844,
      "word": "dein"
    },
    {
      "end": 202.63999938964844,
      "start": 201.44000244140625,
      "word": "Gr\u00fc\u00dfe"
    },
    {
      "end": 203.3000030517578,
      "start": 202.63999938964844,
      "word": "mir"
    },
    {
      "end": 204.75999450683594,
      "start": 203.3000030517578,
      "word": "Vater"
    },
    {
      "end": 205.60000610351562,
      "start": 204.75999450683594,
      "word": "und"
    },
    {
      "end": 205.97999572753906,
      "start": 205.60000610351562,
      "word": "Mutter"
    },
    {
      "end": 206.67999267578125,
      "start": 205.97999572753906,
      "word": "Was"
    },
    {
      "end": 207.25999450683594,
      "start": 206.67999267578125,
      "word": "ist"
    },
    {
      "end": 207.8000030517578,
      "start": 207.4600067138672,
      "word": "Was"
    },
    {
      "end": 208.36000061035156,
      "start": 207.8000030517578,
      "word": "denkst"
    },
    {
      "end": 208.83999633789062,
      "start": 208.36000061035156,
      "word": "du"
    },
    {
      "end": 209.83999633789062,
      "start": 209.66000366210938,
      "word": "Wolltest"
    },
    {
      "end": 210.17999267578125,
      "start": 209.83999633789062,
      "word": "du"
    },
    {
      "end": 210.6999969482422,
      "start": 210.17999267578125,
      "word": "fliehen"
    },
    {
      "end": 211.86000061035156,
      "start": 211.3000030517578,
      "word": "Wohin"
    },
    {
      "end": 212.27999877929688,
      "start": 211.86000061035156,
      "word": "soll"
    },
    {
      "end": 212.47999572753906,
      "start": 212.27999877929688,
      "word": "ich"
    },
    {
      "end": 212.8800048828125,
      "start": 212.47999572753906,
      "word": "dir"
    },
    {
      "end": 214.05999755859375,
      "start": 212.8800048828125,
      "word": "folgen"
    },
    {
      "end": 231.44000244140625,
      "start": 230.0399932861328,
      "word": "Bl\u00fchtest"
    },
    {
      "end": 232.22000122070312,
      "start": 231.44000244140625,
      "word": "du"
    },
    {
      "end": 233.83999633789062,
      "start": 232.22000122070312,
      "word": "nicht"
    },
    {
      "end": 238.24000549316406,
      "start": 236.83999633789062,
      "word": "Hier"
    },
    {
      "end": 239.66000366210938,
      "start": 238.24000549316406,
      "word": "bleib"
    },
    {
      "end": 240.75999450683594,
      "start": 240.55999755859375,
      "word": "ich"
    },
    {
      "end": 247.17999267578125,
      "start": 245.77999877929688,
      "word": "Tristan"
    },
    {
      "end": 248.5800018310547,
      "start": 247.17999267578125,
      "word": "will"
    },
    {
      "end": 249.33999633789062,
      "start": 249.33999633789062,
      "word": "ich"
    },
    {
      "end": 252.47999572753906,
      "start": 249.33999633789062,
      "word": "erwarten"
    },
    {
      "end": 256.82000732421875,
      "start": 255.1199951171875,
      "word": "Betreube"
    },
    {
      "end": 258.20001220703125,
      "start": 257.4599914550781,
      "word": "folg"
    },
    {
      "end": 258.20001220703125,
      "start": 258.20001220703125,
      "word": "was"
    },
    {
      "end": 258.8800048828125,
      "start": 258.20001220703125,
      "word": "ich"
    },
    {
      "end": 260.9800109863281,
      "start": 258.8800048828125,
      "word": "befehle"
    },
    {
      "end": 263.17999267578125,
      "start": 261.9800109863281,
      "word": "Den"
    },
    {
      "end": 265.82000732421875,
      "start": 263.17999267578125,
      "word": "S\u00fcdeltrank"
    },
    {
      "end": 266.7799987792969,
      "start": 265.82000732421875,
      "word": "r\u00fcspe"
    },
    {
      "end": 268.0,
      "start": 266.7799987792969,
      "word": "schnell"
    },
    {
      "end": 270.8999938964844,
      "start": 270.3599853515625,
      "word": "Du"
    },
    {
      "end": 270.94000244140625,
      "start": 270.8999938964844,
      "word": "wei\u00dft"
    },
    {
      "end": 271.4599914550781,
      "start": 271.260009765625,
      "word": "den"
    },
    {
      "end": 271.67999267578125,
      "start": 271.4599914550781,
      "word": "ich"
    },
    {
      "end": 272.0,
      "start": 271.67999267578125,
      "word": "dir"
    },
    {
      "end": 273.1600036621094,
      "start": 272.0,
      "word": "wies"
    },
    {
      "end": 273.6600036621094,
      "start": 273.55999755859375,
      "word": "Und"
    },
    {
      "end": 274.3599853515625,
      "start": 273.6600036621094,
      "word": "welchen"
    },
    {
      "end": 275.55999755859375,
      "start": 274.3599853515625,
      "word": "Trank"
    },
    {
      "end": 278.0799865722656,
      "start": 276.55999755859375,
      "word": "Welcher"
    },
    {
      "end": 279.67999267578125,
      "start": 278.0799865722656,
      "word": "Trank"
    },
    {
      "end": 280.9200134277344,
      "start": 279.8800048828125,
      "word": "In"
    },
    {
      "end": 281.2799987792969,
      "start": 280.9200134277344,
      "word": "die"
    },
    {
      "end": 282.5400085449219,
      "start": 281.2799987792969,
      "word": "goldene"
    },
    {
      "end": 283.32000732421875,
      "start": 282.5400085449219,
      "word": "Schale"
    },
    {
      "end": 283.8599853515625,
      "start": 283.32000732421875,
      "word": "gie\u00df"
    },
    {
      "end": 284.20001220703125,
      "start": 283.8599853515625,
      "word": "er"
    },
    {
      "end": 285.05999755859375,
      "start": 284.20001220703125,
      "word": "aus"
    },
    {
      "end": 286.9200134277344,
      "start": 285.5199890136719,
      "word": "Gef\u00fcllt"
    },
    {
      "end": 287.8800048828125,
      "start": 286.9200134277344,
      "word": "fasst"
    },
    {
      "end": 288.260009765625,
      "start": 287.8800048828125,
      "word": "sie"
    },
    {
      "end": 288.94000244140625,
      "start": 288.260009765625,
      "word": "ihn"
    },
    {
      "end": 289.79998779296875,
      "start": 288.94000244140625,
      "word": "ganz"
    },
    {
      "end": 320.1400146484375,
      "start": 319.79998779296875,
      "word": "Kennst"
    },
    {
      "end": 320.2799987792969,
      "start": 320.1400146484375,
      "word": "du"
    },
    {
      "end": 320.5400085449219,
      "start": 320.2799987792969,
      "word": "der"
    },
    {
      "end": 321.20001220703125,
      "start": 320.5400085449219,
      "word": "Mutter"
    },
    {
      "end": 322.0199890136719,
      "start": 321.20001220703125,
      "word": "K\u00fcnste"
    },
    {
      "end": 322.7799987792969,
      "start": 322.0199890136719,
      "word": "nicht"
    },
    {
      "end": 325.44000244140625,
      "start": 325.4200134277344,
      "word": "Denkst"
    },
    {
      "end": 325.55999755859375,
      "start": 325.44000244140625,
      "word": "du"
    },
    {
      "end": 325.9800109863281,
      "start": 325.94000244140625,
      "word": "die"
    },
    {
      "end": 326.94000244140625,
      "start": 325.9800109863281,
      "word": "alles"
    },
    {
      "end": 328.2799987792969,
      "start": 326.94000244140625,
      "word": "klug"
    },
    {
      "end": 328.9800109863281,
      "start": 328.2799987792969,
      "word": "erweckt"
    },
    {
      "end": 333.3800048828125,
      "start": 332.3999938964844,
      "word": "Ohne"
    },
    {
      "end": 334.1000061035156,
      "start": 333.3800048828125,
      "word": "Rat"
    },
    {
      "end": 334.55999755859375,
      "start": 334.1000061035156,
      "word": "im"
    },
    {
      "end": 335.6600036621094,
      "start": 334.55999755859375,
      "word": "Fremdes"
    },
    {
      "end": 336.5199890136719,
      "start": 335.6600036621094,
      "word": "Land"
    },
    {
      "end": 337.3399963378906,
      "start": 336.5199890136719,
      "word": "H\u00e4tt"
    },
    {
      "end": 337.6199951171875,
      "start": 337.3399963378906,
      "word": "sie"
    },
    {
      "end": 338.1000061035156,
      "start": 337.6199951171875,
      "word": "mit"
    },
    {
      "end": 339.1600036621094,
      "start": 338.1000061035156,
      "word": "Wehe"
    },
    {
      "end": 340.32000732421875,
      "start": 339.1600036621094,
      "word": "mich"
    },
    {
      "end": 342.79998779296875,
      "start": 340.32000732421875,
      "word": "entsandt"
    },
    {
      "end": 349.5199890136719,
      "start": 348.1199951171875,
      "word": "Wehe"
    },
    {
      "end": 349.9200134277344,
      "start": 349.5199890136719,
      "word": "und"
    },
    {
      "end": 351.239990234375,
      "start": 349.9200134277344,
      "word": "Wunden"
    },
    {
      "end": 352.239990234375,
      "start": 351.239990234375,
      "word": "gab"
    },
    {
      "end": 353.05999755859375,
      "start": 352.239990234375,
      "word": "sie"
    },
    {
      "end": 356.4599914550781,
      "start": 353.05999755859375,
      "word": "wahrsam"
    },
    {
      "end": 360.4599914550781,
      "start": 359.8800048828125,
      "word": "F\u00fcr"
    },
    {
      "end": 361.760009765625,
      "start": 360.4599914550781,
      "word": "b\u00f6se"
    },
    {
      "end": 363.1199951171875,
      "start": 361.760009765625,
      "word": "Gifte"
    },
    {
      "end": 365.8599853515625,
      "start": 363.1199951171875,
      "word": "jeden"
    },
    {
      "end": 367.1400146484375,
      "start": 365.8599853515625,
      "word": "gibt"
    },
    {
      "end": 375.0799865722656,
      "start": 373.67999267578125,
      "word": "Der"
    },
    {
      "end": 376.4800109863281,
      "start": 375.0799865722656,
      "word": "tiefstes"
    },
    {
      "end": 378.3999938964844,
      "start": 376.4800109863281,
      "word": "Weh"
    },
    {
      "end": 391.5,
      "start": 390.1000061035156,
      "word": "Der"
    },
    {
      "end": 392.8999938964844,
      "start": 391.5,
      "word": "h\u00f6chstes"
    },
    {
      "end": 396.0799865722656,
      "start": 392.8999938964844,
      "word": "Leid"
    },
    {
      "end": 399.9200134277344,
      "start": 396.0799865722656,
      "word": "Gab"
    },
    {
      "end": 401.17999267578125,
      "start": 399.9200134277344,
      "word": "sie"
    },
    {
      "end": 401.94000244140625,
      "start": 401.17999267578125,
      "word": "den"
    },
    {
      "end": 405.3599853515625,
      "start": 401.94000244140625,
      "word": "Todestrank"
    },
    {
      "end": 415.5400085449219,
      "start": 414.1400146484375,
      "word": "Ihr"
    },
    {
      "end": 416.94000244140625,
      "start": 415.5400085449219,
      "word": "Tod"
    },
    {
      "end": 418.5799865722656,
      "start": 416.94000244140625,
      "word": "nun"
    },
    {
      "end": 420.6400146484375,
      "start": 418.5799865722656,
      "word": "sag"
    },
    {
      "end": 422.44000244140625,
      "start": 420.7799987792969,
      "word": "ihr"
    },
    {
      "end": 423.3999938964844,
      "start": 422.44000244140625,
      "word": "Dank"
    },
    {
      "end": 424.2200012207031,
      "start": 423.3999938964844,
      "word": "Ihr"
    },
    {
      "end": 424.2200012207031,
      "start": 424.2200012207031,
      "word": "Tod"
    },
    {
      "end": 424.2200012207031,
      "start": 424.2200012207031,
      "word": "nun"
    },
    {
      "end": 424.2200012207031,
      "start": 424.2200012207031,
      "word": "sag"
    },
    {
      "end": 427.239990234375,
      "start": 427.2200012207031,
      "word": "ihr"
    },
    {
      "end": 431.94000244140625,
      "start": 427.239990234375,
      "word": "Dank"
    },
    {
      "end": 438.67999267578125,
      "start": 437.2799987792969,
      "word": "Oh"
    },
    {
      "end": 440.0799865722656,
      "start": 438.67999267578125,
      "word": "tiefstes"
    },
    {
      "end": 440.94000244140625,
      "start": 440.0799865722656,
      "word": "Weh"
    },
    {
      "end": 444.0199890136719,
      "start": 442.6199951171875,
      "word": "Oh"
    },
    {
      "end": 444.0199890136719,
      "start": 444.0199890136719,
      "word": "tiefstes"
    },
    {
      "end": 444.0199890136719,
      "start": 444.0199890136719,
      "word": "Weh"
    },
    {
      "end": 444.4599914550781,
      "start": 444.0199890136719,
      "word": "H\u00f6rst"
    },
    {
      "end": 444.94000244140625,
      "start": 444.4599914550781,
      "word": "du"
    },
    {
      "end": 445.6400146484375,
      "start": 444.94000244140625,
      "word": "mir"
    },
    {
      "end": 446.94000244140625,
      "start": 445.6400146484375,
      "word": "nach"
    },
    {
      "end": 452.760009765625,
      "start": 451.3599853515625,
      "word": "Oh"
    },
    {
      "end": 454.1600036621094,
      "start": 452.760009765625,
      "word": "h\u00f6chstes"
    },
    {
      "end": 454.8999938964844,
      "start": 454.1600036621094,
      "word": "Leid"
    },
    {
      "end": 455.1000061035156,
      "start": 454.9599914550781,
      "word": "Oh"
    },
    {
      "end": 455.1000061035156,
      "start": 455.1000061035156,
      "word": "h\u00f6chstes"
    },
    {
      "end": 455.1000061035156,
      "start": 455.1000061035156,
      "word": "Leid"
    },
    {
      "end": 456.239990234375,
      "start": 455.5,
      "word": "Bist"
    },
    {
      "end": 456.6000061035156,
      "start": 456.239990234375,
      "word": "du"
    },
    {
      "end": 457.29998779296875,
      "start": 456.6000061035156,
      "word": "betroffen"
    },
    {
      "end": 459.1600036621094,
      "start": 458.70001220703125,
      "word": "Ja"
    },
    {
      "end": 460.2799987792969,
      "start": 459.739990234375,
      "word": "Tristan"
    },
    {
      "end": 461.94000244140625,
      "start": 461.94000244140625,
      "word": "Ja"
    },
    {
      "end": 463.94000244140625,
      "start": 461.94000244140625,
      "word": "Tristan"
    },
    {
      "end": 490.5199890136719,
      "start": 489.1199951171875,
      "word": "Herr"
    },
    {
      "end": 491.9200134277344,
      "start": 490.5199890136719,
      "word": "Tristan"
    },
    {
      "end": 499.0400085449219,
      "start": 497.6400146484375,
      "word": "Herr"
    },
    {
      "end": 499.0400085449219,
      "start": 499.0400085449219,
      "word": "Tristan"
    },
    {
      "end": 499.0400085449219,
      "start": 499.0199890136719,
      "word": "r"
    }
  ],
  "task": "transcribe"
}