{
  "duration": 495.3299865722656,
  "language": "german",
  "text": "Ludo, Ludo, neidlicher Schwert, Was musstest du zerspringen? Freund und Schuh, dich die Starbe fragt, Im Wied' rat' ich dich enden! Lase mal, lase die Blut! Bild im Walde mutzt ein Baum, Dem hab' ich im Horst gefehlt. Die braune Esche brennt, Geh' zur Kuhl, auf dem Hirt nur klingeln Die Gefeuer. Lase mal, lase die Blut! Das Baumes Wohle, wie brennt sie gl\u00fcht, Wie gl\u00fcht sie hell und d\u00fcnn! Mit springenden Furchen spr\u00fcht sie auf, Verschlie\u00dft mir des Stahles Freude, Lase mal, lase die Blut! Der St\u00fcrme versperrt und Wagner f\u00e4llt, Das sieht nun deutlich wohl aus, Wort und Ring erregt ihr im Hals, Wie erwerbe ich mir den Gewinn? Mit Witz und Fliss gewinne ich beides, Und werde heil mein Horst! Hahahaha!  Lange sie schm\u00fcht mit dem Wurm, Von der M\u00fche erlaub' ihn ein Trub, Aus w\u00fcrzigen S\u00e4ften, die ich gesammelt brau' ich, Der beste Trank f\u00fcr ihn. Wenig Tropfen nur braucht er zu trinken, Sehnlos sinkt er im Schlaf. Mit der eigenen Waffe, die er sich gewonnen, R\u00e4um' ich ihm leicht aus dem Weg, Erlaub' ihm Regen und Boden. Du neidliches Spiel, Du schwarz, deines Stahles streu, Mit eigenem Speise springst du. Denn welcher Wurm, mein feiner Wichs, Hat dich mir wohl rat? Bald schwing' ich dich als mein Schwert In das Wasserfluss, mein Feuerfluss, Grimmiger Zorn zieh' ich ihm da auf, Wie Seele verfloss in des Wassers Blut, Flie\u00dft er nicht mehr. Stark ward er und steif Erricht' der harte Stahl Hei\u00dfes Blut da Flie\u00dft ihm bald Und schwitze noch einmal Dass ich dich schweige. Du neidliches Spiel Was schafft der T\u00f6lpe dort mit dem Topf? Brenn' ich hier Stahl, Braust du dort Zudel? Zu standen kam ein Schmied, Den Lehrer sein Knabe lehrt. Mit der Brust nur isst dein Alten aus, Als Koch dient er dem Kind, Brennt es das Eisen zu frei. Aus Eiern braut der Alte ihm Sud. Niemand, der K\u00fcnstler, lernt jetzt kochen, Das Spielen weckt ihm nicht mehr. Seine schwerhafte Balle hab' ich das Wissen, Was er braucht, ich kost' es ihm nicht. Das F\u00fchrchen zu lernen, wie er dich f\u00fchren, Ein Kerner soll es nicht lehren. Was am besten er kann, mir bringt es nicht bei. Als Pimpern besteht er hin.",
  "segments": null,
  "words": [
    {
      "end": 2.0799999237060547,
      "start": 0.0,
      "word": "Ludo"
    },
    {
      "end": 4.739999771118164,
      "start": 4.579999923706055,
      "word": "Ludo"
    },
    {
      "end": 6.559999942779541,
      "start": 6.300000190734863,
      "word": "neidlicher"
    },
    {
      "end": 8.140000343322754,
      "start": 6.559999942779541,
      "word": "Schwert"
    },
    {
      "end": 9.260000228881836,
      "start": 8.600000381469727,
      "word": "Was"
    },
    {
      "end": 10.199999809265137,
      "start": 9.260000228881836,
      "word": "musstest"
    },
    {
      "end": 11.15999984741211,
      "start": 10.199999809265137,
      "word": "du"
    },
    {
      "end": 12.979999542236328,
      "start": 11.15999984741211,
      "word": "zerspringen"
    },
    {
      "end": 18.079999923706055,
      "start": 16.68000030517578,
      "word": "Freund"
    },
    {
      "end": 18.739999771118164,
      "start": 18.079999923706055,
      "word": "und"
    },
    {
      "end": 19.540000915527344,
      "start": 18.739999771118164,
      "word": "Schuh"
    },
    {
      "end": 20.399999618530273,
      "start": 20.219999313354492,
      "word": "dich"
    },
    {
      "end": 20.700000762939453,
      "start": 20.399999618530273,
      "word": "die"
    },
    {
      "end": 22.760000228881836,
      "start": 20.700000762939453,
      "word": "Starbe"
    },
    {
      "end": 24.18000030517578,
      "start": 22.760000228881836,
      "word": "fragt"
    },
    {
      "end": 25.040000915527344,
      "start": 24.18000030517578,
      "word": "Im"
    },
    {
      "end": 26.540000915527344,
      "start": 25.040000915527344,
      "word": "Wied"
    },
    {
      "end": 28.65999984741211,
      "start": 27.1200008392334,
      "word": "rat"
    },
    {
      "end": 29.0,
      "start": 28.65999984741211,
      "word": "ich"
    },
    {
      "end": 29.780000686645508,
      "start": 29.0,
      "word": "dich"
    },
    {
      "end": 31.18000030517578,
      "start": 29.780000686645508,
      "word": "enden"
    },
    {
      "end": 45.58000183105469,
      "start": 44.18000030517578,
      "word": "Lase"
    },
    {
      "end": 46.97999954223633,
      "start": 45.58000183105469,
      "word": "mal"
    },
    {
      "end": 49.31999969482422,
      "start": 49.31999969482422,
      "word": "lase"
    },
    {
      "end": 49.959999084472656,
      "start": 49.31999969482422,
      "word": "die"
    },
    {
      "end": 52.15999984741211,
      "start": 49.959999084472656,
      "word": "Blut"
    },
    {
      "end": 63.0,
      "start": 61.599998474121094,
      "word": "Bild"
    },
    {
      "end": 63.7400016784668,
      "start": 63.0,
      "word": "im"
    },
    {
      "end": 65.87999725341797,
      "start": 63.7400016784668,
      "word": "Walde"
    },
    {
      "end": 67.27999877929688,
      "start": 65.87999725341797,
      "word": "mutzt"
    },
    {
      "end": 67.9000015258789,
      "start": 67.27999877929688,
      "word": "ein"
    },
    {
      "end": 68.94000244140625,
      "start": 67.9000015258789,
      "word": "Baum"
    },
    {
      "end": 69.94000244140625,
      "start": 69.41999816894531,
      "word": "Dem"
    },
    {
      "end": 71.13999938964844,
      "start": 69.94000244140625,
      "word": "hab"
    },
    {
      "end": 71.44000244140625,
      "start": 71.37999725341797,
      "word": "ich"
    },
    {
      "end": 72.23999786376953,
      "start": 71.44000244140625,
      "word": "im"
    },
    {
      "end": 73.36000061035156,
      "start": 72.23999786376953,
      "word": "Horst"
    },
    {
      "end": 77.66000366210938,
      "start": 73.36000061035156,
      "word": "gefehlt"
    },
    {
      "end": 78.5,
      "start": 77.66000366210938,
      "word": "Die"
    },
    {
      "end": 80.63999938964844,
      "start": 78.5,
      "word": "braune"
    },
    {
      "end": 82.77999877929688,
      "start": 80.63999938964844,
      "word": "Esche"
    },
    {
      "end": 84.0999984741211,
      "start": 82.77999877929688,
      "word": "brennt"
    },
    {
      "end": 84.73999786376953,
      "start": 84.4000015258789,
      "word": "Geh"
    },
    {
      "end": 85.0199966430664,
      "start": 84.76000213623047,
      "word": "zur"
    },
    {
      "end": 86.73999786376953,
      "start": 85.0199966430664,
      "word": "Kuhl"
    },
    {
      "end": 86.87999725341797,
      "start": 86.81999969482422,
      "word": "auf"
    },
    {
      "end": 87.26000213623047,
      "start": 86.87999725341797,
      "word": "dem"
    },
    {
      "end": 88.54000091552734,
      "start": 87.26000213623047,
      "word": "Hirt"
    },
    {
      "end": 89.37999725341797,
      "start": 88.54000091552734,
      "word": "nur"
    },
    {
      "end": 90.44000244140625,
      "start": 89.37999725341797,
      "word": "klingeln"
    },
    {
      "end": 91.95999908447266,
      "start": 90.55999755859375,
      "word": "Die"
    },
    {
      "end": 93.36000061035156,
      "start": 91.95999908447266,
      "word": "Gefeuer"
    },
    {
      "end": 108.23999786376953,
      "start": 106.83999633789062,
      "word": "Lase"
    },
    {
      "end": 109.63999938964844,
      "start": 108.23999786376953,
      "word": "mal"
    },
    {
      "end": 112.19999694824219,
      "start": 112.19999694824219,
      "word": "lase"
    },
    {
      "end": 113.05999755859375,
      "start": 112.19999694824219,
      "word": "die"
    },
    {
      "end": 114.4000015258789,
      "start": 113.05999755859375,
      "word": "Blut"
    },
    {
      "end": 125.33999633789062,
      "start": 123.94000244140625,
      "word": "Das"
    },
    {
      "end": 126.73999786376953,
      "start": 125.33999633789062,
      "word": "Baumes"
    },
    {
      "end": 128.1999969482422,
      "start": 126.73999786376953,
      "word": "Wohle"
    },
    {
      "end": 128.9199981689453,
      "start": 128.9199981689453,
      "word": "wie"
    },
    {
      "end": 130.52000427246094,
      "start": 128.9199981689453,
      "word": "brennt"
    },
    {
      "end": 130.9199981689453,
      "start": 130.52000427246094,
      "word": "sie"
    },
    {
      "end": 131.83999633789062,
      "start": 130.9199981689453,
      "word": "gl\u00fcht"
    },
    {
      "end": 133.02000427246094,
      "start": 132.5399932861328,
      "word": "Wie"
    },
    {
      "end": 134.4199981689453,
      "start": 133.02000427246094,
      "word": "gl\u00fcht"
    },
    {
      "end": 135.0800018310547,
      "start": 134.4199981689453,
      "word": "sie"
    },
    {
      "end": 136.60000610351562,
      "start": 135.0800018310547,
      "word": "hell"
    },
    {
      "end": 137.39999389648438,
      "start": 136.60000610351562,
      "word": "und"
    },
    {
      "end": 139.36000061035156,
      "start": 137.39999389648438,
      "word": "d\u00fcnn"
    },
    {
      "end": 141.5,
      "start": 140.9199981689453,
      "word": "Mit"
    },
    {
      "end": 142.44000244140625,
      "start": 141.5,
      "word": "springenden"
    },
    {
      "end": 143.72000122070312,
      "start": 142.44000244140625,
      "word": "Furchen"
    },
    {
      "end": 144.4199981689453,
      "start": 143.72000122070312,
      "word": "spr\u00fcht"
    },
    {
      "end": 144.72000122070312,
      "start": 144.4199981689453,
      "word": "sie"
    },
    {
      "end": 145.67999267578125,
      "start": 144.72000122070312,
      "word": "auf"
    },
    {
      "end": 152.10000610351562,
      "start": 150.6999969482422,
      "word": "Verschlie\u00dft"
    },
    {
      "end": 152.4199981689453,
      "start": 152.10000610351562,
      "word": "mir"
    },
    {
      "end": 152.6999969482422,
      "start": 152.4199981689453,
      "word": "des"
    },
    {
      "end": 155.05999755859375,
      "start": 152.6999969482422,
      "word": "Stahles"
    },
    {
      "end": 157.1199951171875,
      "start": 155.05999755859375,
      "word": "Freude"
    },
    {
      "end": 171.66000366210938,
      "start": 170.25999450683594,
      "word": "Lase"
    },
    {
      "end": 173.05999755859375,
      "start": 171.66000366210938,
      "word": "mal"
    },
    {
      "end": 176.1999969482422,
      "start": 176.1999969482422,
      "word": "lase"
    },
    {
      "end": 177.1199951171875,
      "start": 176.1999969482422,
      "word": "die"
    },
    {
      "end": 178.72000122070312,
      "start": 177.1199951171875,
      "word": "Blut"
    },
    {
      "end": 181.25999450683594,
      "start": 179.72000122070312,
      "word": "Der"
    },
    {
      "end": 182.8000030517578,
      "start": 181.25999450683594,
      "word": "St\u00fcrme"
    },
    {
      "end": 184.27999877929688,
      "start": 182.8000030517578,
      "word": "versperrt"
    },
    {
      "end": 185.1999969482422,
      "start": 184.27999877929688,
      "word": "und"
    },
    {
      "end": 186.86000061035156,
      "start": 185.1999969482422,
      "word": "Wagner"
    },
    {
      "end": 187.82000732421875,
      "start": 186.86000061035156,
      "word": "f\u00e4llt"
    },
    {
      "end": 189.67999267578125,
      "start": 188.9199981689453,
      "word": "Das"
    },
    {
      "end": 190.4199981689453,
      "start": 189.67999267578125,
      "word": "sieht"
    },
    {
      "end": 190.77999877929688,
      "start": 190.4199981689453,
      "word": "nun"
    },
    {
      "end": 191.97999572753906,
      "start": 190.77999877929688,
      "word": "deutlich"
    },
    {
      "end": 192.4199981689453,
      "start": 191.97999572753906,
      "word": "wohl"
    },
    {
      "end": 193.1199951171875,
      "start": 192.4199981689453,
      "word": "aus"
    },
    {
      "end": 194.82000732421875,
      "start": 194.82000732421875,
      "word": "Wort"
    },
    {
      "end": 195.32000732421875,
      "start": 194.82000732421875,
      "word": "und"
    },
    {
      "end": 196.24000549316406,
      "start": 195.32000732421875,
      "word": "Ring"
    },
    {
      "end": 197.89999389648438,
      "start": 196.24000549316406,
      "word": "erregt"
    },
    {
      "end": 198.10000610351562,
      "start": 197.89999389648438,
      "word": "ihr"
    },
    {
      "end": 198.39999389648438,
      "start": 198.10000610351562,
      "word": "im"
    },
    {
      "end": 199.10000610351562,
      "start": 198.39999389648438,
      "word": "Hals"
    },
    {
      "end": 201.02000427246094,
      "start": 200.3800048828125,
      "word": "Wie"
    },
    {
      "end": 201.63999938964844,
      "start": 201.02000427246094,
      "word": "erwerbe"
    },
    {
      "end": 201.94000244140625,
      "start": 201.63999938964844,
      "word": "ich"
    },
    {
      "end": 202.17999267578125,
      "start": 201.94000244140625,
      "word": "mir"
    },
    {
      "end": 202.60000610351562,
      "start": 202.17999267578125,
      "word": "den"
    },
    {
      "end": 203.02000427246094,
      "start": 202.60000610351562,
      "word": "Gewinn"
    },
    {
      "end": 206.1199951171875,
      "start": 204.97999572753906,
      "word": "Mit"
    },
    {
      "end": 206.55999755859375,
      "start": 206.1199951171875,
      "word": "Witz"
    },
    {
      "end": 207.10000610351562,
      "start": 206.55999755859375,
      "word": "und"
    },
    {
      "end": 207.6999969482422,
      "start": 207.10000610351562,
      "word": "Fliss"
    },
    {
      "end": 208.36000061035156,
      "start": 207.6999969482422,
      "word": "gewinne"
    },
    {
      "end": 208.63999938964844,
      "start": 208.36000061035156,
      "word": "ich"
    },
    {
      "end": 209.52000427246094,
      "start": 208.63999938964844,
      "word": "beides"
    },
    {
      "end": 210.24000549316406,
      "start": 209.94000244140625,
      "word": "Und"
    },
    {
      "end": 210.4600067138672,
      "start": 210.24000549316406,
      "word": "werde"
    },
    {
      "end": 211.33999633789062,
      "start": 210.4600067138672,
      "word": "heil"
    },
    {
      "end": 211.63999938964844,
      "start": 211.33999633789062,
      "word": "mein"
    },
    {
      "end": 212.2100067138672,
      "start": 211.63999938964844,
      "word": "Horst"
    },
    {
      "end": 214.19000244140625,
      "start": 213.30999755859375,
      "word": "Hahahaha"
    },
    {
      "end": 224.49000549316406,
      "start": 223.61000061035156,
      "word": "Lange"
    },
    {
      "end": 224.88999938964844,
      "start": 224.49000549316406,
      "word": "sie"
    },
    {
      "end": 226.27000427246094,
      "start": 224.88999938964844,
      "word": "schm\u00fcht"
    },
    {
      "end": 226.6300048828125,
      "start": 226.27000427246094,
      "word": "mit"
    },
    {
      "end": 228.1300048828125,
      "start": 226.6300048828125,
      "word": "dem"
    },
    {
      "end": 229.64999389648438,
      "start": 228.1300048828125,
      "word": "Wurm"
    },
    {
      "end": 230.19000244140625,
      "start": 230.08999633789062,
      "word": "Von"
    },
    {
      "end": 230.5500030517578,
      "start": 230.19000244140625,
      "word": "der"
    },
    {
      "end": 231.85000610351562,
      "start": 230.5500030517578,
      "word": "M\u00fche"
    },
    {
      "end": 233.35000610351562,
      "start": 231.85000610351562,
      "word": "erlaub"
    },
    {
      "end": 233.64999389648438,
      "start": 233.38999938964844,
      "word": "ihn"
    },
    {
      "end": 234.08999633789062,
      "start": 233.64999389648438,
      "word": "ein"
    },
    {
      "end": 234.3699951171875,
      "start": 234.08999633789062,
      "word": "Trub"
    },
    {
      "end": 236.1699981689453,
      "start": 235.97000122070312,
      "word": "Aus"
    },
    {
      "end": 237.14999389648438,
      "start": 236.1699981689453,
      "word": "w\u00fcrzigen"
    },
    {
      "end": 237.88999938964844,
      "start": 237.14999389648438,
      "word": "S\u00e4ften"
    },
    {
      "end": 238.35000610351562,
      "start": 238.11000061035156,
      "word": "die"
    },
    {
      "end": 238.58999633789062,
      "start": 238.35000610351562,
      "word": "ich"
    },
    {
      "end": 239.02999877929688,
      "start": 238.58999633789062,
      "word": "gesammelt"
    },
    {
      "end": 239.61000061035156,
      "start": 239.02999877929688,
      "word": "brau"
    },
    {
      "end": 239.88999938964844,
      "start": 239.6699981689453,
      "word": "ich"
    },
    {
      "end": 240.08999633789062,
      "start": 239.88999938964844,
      "word": "Der"
    },
    {
      "end": 240.08999633789062,
      "start": 240.08999633789062,
      "word": "beste"
    },
    {
      "end": 240.85000610351562,
      "start": 240.08999633789062,
      "word": "Trank"
    },
    {
      "end": 241.7899932861328,
      "start": 240.85000610351562,
      "word": "f\u00fcr"
    },
    {
      "end": 242.77000427246094,
      "start": 241.7899932861328,
      "word": "ihn"
    },
    {
      "end": 244.5500030517578,
      "start": 244.22999572753906,
      "word": "Wenig"
    },
    {
      "end": 245.52999877929688,
      "start": 244.5500030517578,
      "word": "Tropfen"
    },
    {
      "end": 246.08999633789062,
      "start": 245.52999877929688,
      "word": "nur"
    },
    {
      "end": 246.50999450683594,
      "start": 246.08999633789062,
      "word": "braucht"
    },
    {
      "end": 246.88999938964844,
      "start": 246.50999450683594,
      "word": "er"
    },
    {
      "end": 247.6300048828125,
      "start": 246.88999938964844,
      "word": "zu"
    },
    {
      "end": 248.49000549316406,
      "start": 247.6300048828125,
      "word": "trinken"
    },
    {
      "end": 251.91000366210938,
      "start": 250.85000610351562,
      "word": "Sehnlos"
    },
    {
      "end": 252.8300018310547,
      "start": 251.91000366210938,
      "word": "sinkt"
    },
    {
      "end": 253.2100067138672,
      "start": 252.8300018310547,
      "word": "er"
    },
    {
      "end": 253.75,
      "start": 253.2100067138672,
      "word": "im"
    },
    {
      "end": 254.64999389648438,
      "start": 253.75,
      "word": "Schlaf"
    },
    {
      "end": 255.3300018310547,
      "start": 255.22999572753906,
      "word": "Mit"
    },
    {
      "end": 255.6699981689453,
      "start": 255.3300018310547,
      "word": "der"
    },
    {
      "end": 256.2300109863281,
      "start": 255.6699981689453,
      "word": "eigenen"
    },
    {
      "end": 256.7699890136719,
      "start": 256.2300109863281,
      "word": "Waffe"
    },
    {
      "end": 257.0899963378906,
      "start": 256.7699890136719,
      "word": "die"
    },
    {
      "end": 257.2300109863281,
      "start": 257.0899963378906,
      "word": "er"
    },
    {
      "end": 257.42999267578125,
      "start": 257.2300109863281,
      "word": "sich"
    },
    {
      "end": 258.0299987792969,
      "start": 257.42999267578125,
      "word": "gewonnen"
    },
    {
      "end": 259.3900146484375,
      "start": 259.010009765625,
      "word": "R\u00e4um"
    },
    {
      "end": 259.6300048828125,
      "start": 259.5899963378906,
      "word": "ich"
    },
    {
      "end": 259.7699890136719,
      "start": 259.6300048828125,
      "word": "ihm"
    },
    {
      "end": 260.510009765625,
      "start": 259.7699890136719,
      "word": "leicht"
    },
    {
      "end": 260.7300109863281,
      "start": 260.510009765625,
      "word": "aus"
    },
    {
      "end": 260.9100036621094,
      "start": 260.7300109863281,
      "word": "dem"
    },
    {
      "end": 261.42999267578125,
      "start": 260.9100036621094,
      "word": "Weg"
    },
    {
      "end": 261.7900085449219,
      "start": 261.5299987792969,
      "word": "Erlaub"
    },
    {
      "end": 261.8500061035156,
      "start": 261.80999755859375,
      "word": "ihm"
    },
    {
      "end": 262.6300048828125,
      "start": 261.8500061035156,
      "word": "Regen"
    },
    {
      "end": 263.07000732421875,
      "start": 262.6300048828125,
      "word": "und"
    },
    {
      "end": 264.30999755859375,
      "start": 263.07000732421875,
      "word": "Boden"
    },
    {
      "end": 269.19000244140625,
      "start": 268.1099853515625,
      "word": "Du"
    },
    {
      "end": 270.2699890136719,
      "start": 269.19000244140625,
      "word": "neidliches"
    },
    {
      "end": 271.2300109863281,
      "start": 270.2699890136719,
      "word": "Spiel"
    },
    {
      "end": 273.2300109863281,
      "start": 272.1499938964844,
      "word": "Du"
    },
    {
      "end": 274.30999755859375,
      "start": 273.2300109863281,
      "word": "schwarz"
    },
    {
      "end": 275.07000732421875,
      "start": 274.6300048828125,
      "word": "deines"
    },
    {
      "end": 277.45001220703125,
      "start": 275.07000732421875,
      "word": "Stahles"
    },
    {
      "end": 278.3900146484375,
      "start": 277.45001220703125,
      "word": "streu"
    },
    {
      "end": 281.1700134277344,
      "start": 280.0899963378906,
      "word": "Mit"
    },
    {
      "end": 282.25,
      "start": 281.1700134277344,
      "word": "eigenem"
    },
    {
      "end": 284.2099914550781,
      "start": 282.25,
      "word": "Speise"
    },
    {
      "end": 285.6099853515625,
      "start": 284.2099914550781,
      "word": "springst"
    },
    {
      "end": 286.1499938964844,
      "start": 285.6099853515625,
      "word": "du"
    },
    {
      "end": 286.7699890136719,
      "start": 286.1700134277344,
      "word": "Denn"
    },
    {
      "end": 287.010009765625,
      "start": 286.7699890136719,
      "word": "welcher"
    },
    {
      "end": 287.9100036621094,
      "start": 287.010009765625,
      "word": "Wurm"
    },
    {
      "end": 288.2099914550781,
      "start": 288.1499938964844,
      "word": "mein"
    },
    {
      "end": 288.69000244140625,
      "start": 288.2099914550781,
      "word": "feiner"
    },
    {
      "end": 289.6300048828125,
      "start": 288.69000244140625,
      "word": "Wichs"
    },
    {
      "end": 289.989990234375,
      "start": 289.9700012207031,
      "word": "Hat"
    },
    {
      "end": 290.19000244140625,
      "start": 289.989990234375,
      "word": "dich"
    },
    {
      "end": 290.8500061035156,
      "start": 290.19000244140625,
      "word": "mir"
    },
    {
      "end": 291.1300048828125,
      "start": 290.8500061035156,
      "word": "wohl"
    },
    {
      "end": 291.6700134277344,
      "start": 291.1300048828125,
      "word": "rat"
    },
    {
      "end": 293.54998779296875,
      "start": 292.6700134277344,
      "word": "Bald"
    },
    {
      "end": 294.4700012207031,
      "start": 293.54998779296875,
      "word": "schwing"
    },
    {
      "end": 294.7699890136719,
      "start": 294.4700012207031,
      "word": "ich"
    },
    {
      "end": 295.3299865722656,
      "start": 294.7699890136719,
      "word": "dich"
    },
    {
      "end": 295.42999267578125,
      "start": 295.3299865722656,
      "word": "als"
    },
    {
      "end": 295.80999755859375,
      "start": 295.42999267578125,
      "word": "mein"
    },
    {
      "end": 297.8299865722656,
      "start": 295.80999755859375,
      "word": "Schwert"
    },
    {
      "end": 303.5299987792969,
      "start": 302.6700134277344,
      "word": "In"
    },
    {
      "end": 303.8299865722656,
      "start": 303.5299987792969,
      "word": "das"
    },
    {
      "end": 305.92999267578125,
      "start": 303.8299865722656,
      "word": "Wasserfluss"
    },
    {
      "end": 306.489990234375,
      "start": 306.3299865722656,
      "word": "mein"
    },
    {
      "end": 309.0899963378906,
      "start": 306.489990234375,
      "word": "Feuerfluss"
    },
    {
      "end": 310.6300048828125,
      "start": 310.0899963378906,
      "word": "Grimmiger"
    },
    {
      "end": 311.7900085449219,
      "start": 310.6300048828125,
      "word": "Zorn"
    },
    {
      "end": 312.75,
      "start": 311.7900085449219,
      "word": "zieh"
    },
    {
      "end": 312.989990234375,
      "start": 312.75,
      "word": "ich"
    },
    {
      "end": 313.2300109863281,
      "start": 312.989990234375,
      "word": "ihm"
    },
    {
      "end": 314.19000244140625,
      "start": 313.2300109863281,
      "word": "da"
    },
    {
      "end": 314.489990234375,
      "start": 314.19000244140625,
      "word": "auf"
    },
    {
      "end": 316.7900085449219,
      "start": 315.489990234375,
      "word": "Wie"
    },
    {
      "end": 317.92999267578125,
      "start": 316.7900085449219,
      "word": "Seele"
    },
    {
      "end": 319.30999755859375,
      "start": 317.92999267578125,
      "word": "verfloss"
    },
    {
      "end": 319.95001220703125,
      "start": 319.30999755859375,
      "word": "in"
    },
    {
      "end": 320.3299865722656,
      "start": 319.95001220703125,
      "word": "des"
    },
    {
      "end": 321.8699951171875,
      "start": 320.3299865722656,
      "word": "Wassers"
    },
    {
      "end": 323.1700134277344,
      "start": 321.8699951171875,
      "word": "Blut"
    },
    {
      "end": 326.25,
      "start": 325.9700012207031,
      "word": "Flie\u00dft"
    },
    {
      "end": 327.2300109863281,
      "start": 326.25,
      "word": "er"
    },
    {
      "end": 327.7300109863281,
      "start": 327.2300109863281,
      "word": "nicht"
    },
    {
      "end": 328.5299987792969,
      "start": 327.7300109863281,
      "word": "mehr"
    },
    {
      "end": 330.19000244140625,
      "start": 330.04998779296875,
      "word": "Stark"
    },
    {
      "end": 331.1300048828125,
      "start": 330.19000244140625,
      "word": "ward"
    },
    {
      "end": 331.510009765625,
      "start": 331.1300048828125,
      "word": "er"
    },
    {
      "end": 331.95001220703125,
      "start": 331.510009765625,
      "word": "und"
    },
    {
      "end": 333.4100036621094,
      "start": 331.95001220703125,
      "word": "steif"
    },
    {
      "end": 335.010009765625,
      "start": 333.6099853515625,
      "word": "Erricht"
    },
    {
      "end": 335.4100036621094,
      "start": 335.19000244140625,
      "word": "der"
    },
    {
      "end": 335.95001220703125,
      "start": 335.4100036621094,
      "word": "harte"
    },
    {
      "end": 337.8699951171875,
      "start": 335.95001220703125,
      "word": "Stahl"
    },
    {
      "end": 341.5299987792969,
      "start": 340.1300048828125,
      "word": "Hei\u00dfes"
    },
    {
      "end": 342.8299865722656,
      "start": 341.5299987792969,
      "word": "Blut"
    },
    {
      "end": 346.3500061035156,
      "start": 342.8299865722656,
      "word": "da"
    },
    {
      "end": 346.9100036621094,
      "start": 346.3500061035156,
      "word": "Flie\u00dft"
    },
    {
      "end": 347.45001220703125,
      "start": 346.9100036621094,
      "word": "ihm"
    },
    {
      "end": 349.3500061035156,
      "start": 347.45001220703125,
      "word": "bald"
    },
    {
      "end": 357.0299987792969,
      "start": 355.6300048828125,
      "word": "Und"
    },
    {
      "end": 358.42999267578125,
      "start": 357.0299987792969,
      "word": "schwitze"
    },
    {
      "end": 358.9700012207031,
      "start": 358.42999267578125,
      "word": "noch"
    },
    {
      "end": 360.6099853515625,
      "start": 358.9700012207031,
      "word": "einmal"
    },
    {
      "end": 362.1300048828125,
      "start": 360.6099853515625,
      "word": "Dass"
    },
    {
      "end": 362.6300048828125,
      "start": 362.1300048828125,
      "word": "ich"
    },
    {
      "end": 363.04998779296875,
      "start": 362.6300048828125,
      "word": "dich"
    },
    {
      "end": 364.95001220703125,
      "start": 363.04998779296875,
      "word": "schweige"
    },
    {
      "end": 370.3500061035156,
      "start": 368.95001220703125,
      "word": "Du"
    },
    {
      "end": 371.75,
      "start": 370.3500061035156,
      "word": "neidliches"
    },
    {
      "end": 373.3299865722656,
      "start": 371.75,
      "word": "Spiel"
    },
    {
      "end": 391.0899963378906,
      "start": 390.6099853515625,
      "word": "Was"
    },
    {
      "end": 391.45001220703125,
      "start": 391.0899963378906,
      "word": "schafft"
    },
    {
      "end": 391.75,
      "start": 391.45001220703125,
      "word": "der"
    },
    {
      "end": 392.3699951171875,
      "start": 391.75,
      "word": "T\u00f6lpe"
    },
    {
      "end": 392.80999755859375,
      "start": 392.3699951171875,
      "word": "dort"
    },
    {
      "end": 393.3699951171875,
      "start": 392.80999755859375,
      "word": "mit"
    },
    {
      "end": 393.7699890136719,
      "start": 393.3699951171875,
      "word": "dem"
    },
    {
      "end": 395.4100036621094,
      "start": 393.7699890136719,
      "word": "Topf"
    },
    {
      "end": 398.9100036621094,
      "start": 398.8699951171875,
      "word": "Brenn"
    },
    {
      "end": 399.25,
      "start": 399.25,
      "word": "ich"
    },
    {
      "end": 399.5899963378906,
      "start": 399.25,
      "word": "hier"
    },
    {
      "end": 400.75,
      "start": 399.5899963378906,
      "word": "Stahl"
    },
    {
      "end": 402.6099853515625,
      "start": 402.5299987792969,
      "word": "Braust"
    },
    {
      "end": 403.0299987792969,
      "start": 402.6099853515625,
      "word": "du"
    },
    {
      "end": 403.3699951171875,
      "start": 403.0299987792969,
      "word": "dort"
    },
    {
      "end": 404.3500061035156,
      "start": 403.3699951171875,
      "word": "Zudel"
    },
    {
      "end": 405.2300109863281,
      "start": 404.989990234375,
      "word": "Zu"
    },
    {
      "end": 406.5299987792969,
      "start": 405.2300109863281,
      "word": "standen"
    },
    {
      "end": 407.4100036621094,
      "start": 406.5299987792969,
      "word": "kam"
    },
    {
      "end": 407.7699890136719,
      "start": 407.4100036621094,
      "word": "ein"
    },
    {
      "end": 408.45001220703125,
      "start": 407.7699890136719,
      "word": "Schmied"
    },
    {
      "end": 409.1700134277344,
      "start": 408.95001220703125,
      "word": "Den"
    },
    {
      "end": 409.989990234375,
      "start": 409.1700134277344,
      "word": "Lehrer"
    },
    {
      "end": 410.3500061035156,
      "start": 409.989990234375,
      "word": "sein"
    },
    {
      "end": 411.6099853515625,
      "start": 410.3500061035156,
      "word": "Knabe"
    },
    {
      "end": 412.57000732421875,
      "start": 411.6099853515625,
      "word": "lehrt"
    },
    {
      "end": 413.0299987792969,
      "start": 412.8500061035156,
      "word": "Mit"
    },
    {
      "end": 413.2099914550781,
      "start": 413.0299987792969,
      "word": "der"
    },
    {
      "end": 413.7300109863281,
      "start": 413.2099914550781,
      "word": "Brust"
    },
    {
      "end": 414.04998779296875,
      "start": 413.7300109863281,
      "word": "nur"
    },
    {
      "end": 414.42999267578125,
      "start": 414.04998779296875,
      "word": "isst"
    },
    {
      "end": 414.75,
      "start": 414.42999267578125,
      "word": "dein"
    },
    {
      "end": 415.30999755859375,
      "start": 414.75,
      "word": "Alten"
    },
    {
      "end": 415.8699951171875,
      "start": 415.30999755859375,
      "word": "aus"
    },
    {
      "end": 416.2099914550781,
      "start": 415.8699951171875,
      "word": "Als"
    },
    {
      "end": 416.6099853515625,
      "start": 416.2099914550781,
      "word": "Koch"
    },
    {
      "end": 417.45001220703125,
      "start": 416.6099853515625,
      "word": "dient"
    },
    {
      "end": 418.2099914550781,
      "start": 417.45001220703125,
      "word": "er"
    },
    {
      "end": 419.1099853515625,
      "start": 418.2099914550781,
      "word": "dem"
    },
    {
      "end": 420.3900146484375,
      "start": 419.1099853515625,
      "word": "Kind"
    },
    {
      "end": 421.3699951171875,
      "start": 421.3699951171875,
      "word": "Brennt"
    },
    {
      "end": 421.7300109863281,
      "start": 421.3699951171875,
      "word": "es"
    },
    {
      "end": 422.0899963378906,
      "start": 421.7300109863281,
      "word": "das"
    },
    {
      "end": 422.8500061035156,
      "start": 422.0899963378906,
      "word": "Eisen"
    },
    {
      "end": 423.42999267578125,
      "start": 422.8500061035156,
      "word": "zu"
    },
    {
      "end": 425.4700012207031,
      "start": 423.42999267578125,
      "word": "frei"
    },
    {
      "end": 427.57000732421875,
      "start": 426.95001220703125,
      "word": "Aus"
    },
    {
      "end": 428.8299865722656,
      "start": 427.57000732421875,
      "word": "Eiern"
    },
    {
      "end": 429.989990234375,
      "start": 428.8299865722656,
      "word": "braut"
    },
    {
      "end": 430.54998779296875,
      "start": 429.989990234375,
      "word": "der"
    },
    {
      "end": 431.8500061035156,
      "start": 430.54998779296875,
      "word": "Alte"
    },
    {
      "end": 433.3299865722656,
      "start": 431.8500061035156,
      "word": "ihm"
    },
    {
      "end": 435.489990234375,
      "start": 433.3299865722656,
      "word": "Sud"
    },
    {
      "end": 440.54998779296875,
      "start": 439.6300048828125,
      "word": "Niemand"
    },
    {
      "end": 440.8900146484375,
      "start": 440.57000732421875,
      "word": "der"
    },
    {
      "end": 442.3299865722656,
      "start": 440.8900146484375,
      "word": "K\u00fcnstler"
    },
    {
      "end": 443.57000732421875,
      "start": 443.54998779296875,
      "word": "lernt"
    },
    {
      "end": 444.3900146484375,
      "start": 443.57000732421875,
      "word": "jetzt"
    },
    {
      "end": 445.2300109863281,
      "start": 444.3900146484375,
      "word": "kochen"
    },
    {
      "end": 446.2300109863281,
      "start": 445.9100036621094,
      "word": "Das"
    },
    {
      "end": 447.6499938964844,
      "start": 446.2300109863281,
      "word": "Spielen"
    },
    {
      "end": 448.6499938964844,
      "start": 447.6499938964844,
      "word": "weckt"
    },
    {
      "end": 449.2099914550781,
      "start": 448.6499938964844,
      "word": "ihm"
    },
    {
      "end": 449.8500061035156,
      "start": 449.2099914550781,
      "word": "nicht"
    },
    {
      "end": 450.45001220703125,
      "start": 449.8500061035156,
      "word": "mehr"
    },
    {
      "end": 451.6099853515625,
      "start": 451.30999755859375,
      "word": "Seine"
    },
    {
      "end": 452.3699951171875,
      "start": 451.6099853515625,
      "word": "schwerhafte"
    },
    {
      "end": 453.25,
      "start": 452.3699951171875,
      "word": "Balle"
    },
    {
      "end": 453.510009765625,
      "start": 453.25,
      "word": "hab"
    },
    {
      "end": 453.6099853515625,
      "start": 453.510009765625,
      "word": "ich"
    },
    {
      "end": 454.07000732421875,
      "start": 453.6099853515625,
      "word": "das"
    },
    {
      "end": 454.25,
      "start": 454.07000732421875,
      "word": "Wissen"
    },
    {
      "end": 455.3900146484375,
      "start": 455.2699890136719,
      "word": "Was"
    },
    {
      "end": 455.7300109863281,
      "start": 455.3900146484375,
      "word": "er"
    },
    {
      "end": 456.1700134277344,
      "start": 455.7300109863281,
      "word": "braucht"
    },
    {
      "end": 457.04998779296875,
      "start": 456.6300048828125,
      "word": "ich"
    },
    {
      "end": 457.3900146484375,
      "start": 457.04998779296875,
      "word": "kost"
    },
    {
      "end": 457.6300048828125,
      "start": 457.3900146484375,
      "word": "es"
    },
    {
      "end": 457.75,
      "start": 457.6300048828125,
      "word": "ihm"
    },
    {
      "end": 458.19000244140625,
      "start": 457.75,
      "word": "nicht"
    },
    {
      "end": 472.80999755859375,
      "start": 471.510009765625,
      "word": "Das"
    },
    {
      "end": 474.1099853515625,
      "start": 472.80999755859375,
      "word": "F\u00fchrchen"
    },
    {
      "end": 474.8900146484375,
      "start": 474.1099853515625,
      "word": "zu"
    },
    {
      "end": 475.6300048828125,
      "start": 474.8900146484375,
      "word": "lernen"
    },
    {
      "end": 476.19000244140625,
      "start": 476.1099853515625,
      "word": "wie"
    },
    {
      "end": 476.5899963378906,
      "start": 476.19000244140625,
      "word": "er"
    },
    {
      "end": 476.9100036621094,
      "start": 476.5899963378906,
      "word": "dich"
    },
    {
      "end": 477.8500061035156,
      "start": 476.9100036621094,
      "word": "f\u00fchren"
    },
    {
      "end": 478.8900146484375,
      "start": 478.6099853515625,
      "word": "Ein"
    },
    {
      "end": 480.7099914550781,
      "start": 478.8900146484375,
      "word": "Kerner"
    },
    {
      "end": 482.1499938964844,
      "start": 480.7099914550781,
      "word": "soll"
    },
    {
      "end": 482.7099914550781,
      "start": 482.1499938964844,
      "word": "es"
    },
    {
      "end": 484.3299865722656,
      "start": 482.7099914550781,
      "word": "nicht"
    },
    {
      "end": 484.9700012207031,
      "start": 484.3299865722656,
      "word": "lehren"
    },
    {
      "end": 486.57000732421875,
      "start": 486.25,
      "word": "Was"
    },
    {
      "end": 487.4100036621094,
      "start": 486.57000732421875,
      "word": "am"
    },
    {
      "end": 487.4100036621094,
      "start": 487.4100036621094,
      "word": "besten"
    },
    {
      "end": 487.6300048828125,
      "start": 487.4100036621094,
      "word": "er"
    },
    {
      "end": 488.010009765625,
      "start": 487.6300048828125,
      "word": "kann"
    },
    {
      "end": 488.95001220703125,
      "start": 488.510009765625,
      "word": "mir"
    },
    {
      "end": 489.75,
      "start": 488.95001220703125,
      "word": "bringt"
    },
    {
      "end": 490.3900146484375,
      "start": 489.75,
      "word": "es"
    },
    {
      "end": 491.0299987792969,
      "start": 490.3900146484375,
      "word": "nicht"
    },
    {
      "end": 491.69000244140625,
      "start": 491.0299987792969,
      "word": "bei"
    },
    {
      "end": 493.010009765625,
      "start": 491.69000244140625,
      "word": "Als"
    },
    {
      "end": 493.80999755859375,
      "start": 493.010009765625,
      "word": "Pimpern"
    },
    {
      "end": 494.510009765625,
      "start": 493.80999755859375,
      "word": "besteht"
    },
    {
      "end": 495.010009765625,
      "start": 494.510009765625,
      "word": "er"
    },
    {
      "end": 495.30999755859375,
      "start": 495.010009765625,
      "word": "hin"
    }
  ],
  "task": "transcribe"
}