{
  "duration": 238.92999267578125,
  "language": "italian",
  "text": "Batti, batti, o bel masecco da tua povera zerlina, star\u00f2 qui, com'un gallina, le tue botte ad aspettar. Batti, batti, o bel masecco da tua povera zerlina, star\u00f2 qui, com'un gallina, le tue botte ad aspettar. Lascer\u00f2 straziarmi il crino, lascer\u00f2 cavarmi gli occhi e le gambe, le tue mani e le tue bocce, le tue bocce, le tue bocce. Batti, batti, o bel masecco da tua povera zerlina, star\u00f2 qui, com'un gallina, le tue botte ad aspettar. Batti, batti, o bel masecco da tua povera zerlina, star\u00f2 qui, com'un gallina, le tue botte ad aspettar. Anna, vedo, non hai cuore, Anna, vedo, non hai cuore. Pace, pace, oh vita mia, il pi\u00f9 tendo \u00e8 l'allegria, notte di voglia passare. Notte di voglia passare, notte di voglia passare, notte di voglia passare. Pace, pace, oh vita mia, il pi\u00f9 tendo \u00e8 l'allegria, notte di voglia passare. Si, si, si, si, si, notte di voglia passare. Si, si, si, si, si, notte di voglia passare. Notte di voglia passare, notte di voglia passare.",
  "segments": null,
  "words": [
    {
      "end": 1.4800000190734863,
      "start": 0.0,
      "word": "Batti"
    },
    {
      "end": 2.680000066757202,
      "start": 2.680000066757202,
      "word": "batti"
    },
    {
      "end": 3.0999999046325684,
      "start": 3.0399999618530273,
      "word": "o"
    },
    {
      "end": 3.9200000762939453,
      "start": 3.0999999046325684,
      "word": "bel"
    },
    {
      "end": 5.179999828338623,
      "start": 3.9200000762939453,
      "word": "masecco"
    },
    {
      "end": 6.260000228881836,
      "start": 5.179999828338623,
      "word": "da"
    },
    {
      "end": 6.820000171661377,
      "start": 6.260000228881836,
      "word": "tua"
    },
    {
      "end": 9.119999885559082,
      "start": 6.820000171661377,
      "word": "povera"
    },
    {
      "end": 10.239999771118164,
      "start": 9.119999885559082,
      "word": "zerlina"
    },
    {
      "end": 12.0600004196167,
      "start": 11.579999923706055,
      "word": "star\u00f2"
    },
    {
      "end": 13.0600004196167,
      "start": 12.0600004196167,
      "word": "qui"
    },
    {
      "end": 13.520000457763672,
      "start": 13.4399995803833,
      "word": "com"
    },
    {
      "end": 14.039999961853027,
      "start": 13.520000457763672,
      "word": "un"
    },
    {
      "end": 15.479999542236328,
      "start": 14.039999961853027,
      "word": "gallina"
    },
    {
      "end": 16.579999923706055,
      "start": 16.219999313354492,
      "word": "le"
    },
    {
      "end": 17.139999389648438,
      "start": 16.579999923706055,
      "word": "tue"
    },
    {
      "end": 17.920000076293945,
      "start": 17.139999389648438,
      "word": "botte"
    },
    {
      "end": 19.100000381469727,
      "start": 17.920000076293945,
      "word": "ad"
    },
    {
      "end": 20.799999237060547,
      "start": 19.100000381469727,
      "word": "aspettar"
    },
    {
      "end": 24.940000534057617,
      "start": 23.540000915527344,
      "word": "Batti"
    },
    {
      "end": 26.700000762939453,
      "start": 25.700000762939453,
      "word": "batti"
    },
    {
      "end": 28.440000534057617,
      "start": 27.959999084472656,
      "word": "o"
    },
    {
      "end": 29.219999313354492,
      "start": 28.440000534057617,
      "word": "bel"
    },
    {
      "end": 29.219999313354492,
      "start": 29.219999313354492,
      "word": "masecco"
    },
    {
      "end": 29.219999313354492,
      "start": 29.219999313354492,
      "word": "da"
    },
    {
      "end": 29.219999313354492,
      "start": 29.219999313354492,
      "word": "tua"
    },
    {
      "end": 29.799999237060547,
      "start": 29.219999313354492,
      "word": "povera"
    },
    {
      "end": 30.520000457763672,
      "start": 29.799999237060547,
      "word": "zerlina"
    },
    {
      "end": 32.15999984741211,
      "start": 31.739999771118164,
      "word": "star\u00f2"
    },
    {
      "end": 33.41999816894531,
      "start": 32.15999984741211,
      "word": "qui"
    },
    {
      "end": 36.63999938964844,
      "start": 33.41999816894531,
      "word": "com"
    },
    {
      "end": 36.63999938964844,
      "start": 36.63999938964844,
      "word": "un"
    },
    {
      "end": 36.63999938964844,
      "start": 36.63999938964844,
      "word": "gallina"
    },
    {
      "end": 36.63999938964844,
      "start": 36.63999938964844,
      "word": "le"
    },
    {
      "end": 37.15999984741211,
      "start": 36.63999938964844,
      "word": "tue"
    },
    {
      "end": 38.060001373291016,
      "start": 37.15999984741211,
      "word": "botte"
    },
    {
      "end": 38.779998779296875,
      "start": 38.060001373291016,
      "word": "ad"
    },
    {
      "end": 40.720001220703125,
      "start": 38.779998779296875,
      "word": "aspettar"
    },
    {
      "end": 48.459999084472656,
      "start": 47.060001373291016,
      "word": "Lascer\u00f2"
    },
    {
      "end": 49.41999816894531,
      "start": 48.459999084472656,
      "word": "straziarmi"
    },
    {
      "end": 49.7400016784668,
      "start": 49.41999816894531,
      "word": "il"
    },
    {
      "end": 50.459999084472656,
      "start": 49.7400016784668,
      "word": "crino"
    },
    {
      "end": 58.2599983215332,
      "start": 57.2400016784668,
      "word": "lascer\u00f2"
    },
    {
      "end": 59.08000183105469,
      "start": 58.2599983215332,
      "word": "cavarmi"
    },
    {
      "end": 59.900001525878906,
      "start": 59.08000183105469,
      "word": "gli"
    },
    {
      "end": 60.13999938964844,
      "start": 59.900001525878906,
      "word": "occhi"
    },
    {
      "end": 61.34000015258789,
      "start": 60.13999938964844,
      "word": "e"
    },
    {
      "end": 61.959999084472656,
      "start": 61.34000015258789,
      "word": "le"
    },
    {
      "end": 62.86000061035156,
      "start": 61.959999084472656,
      "word": "gambe"
    },
    {
      "end": 63.220001220703125,
      "start": 62.86000061035156,
      "word": "le"
    },
    {
      "end": 64.04000091552734,
      "start": 63.220001220703125,
      "word": "tue"
    },
    {
      "end": 65.0999984741211,
      "start": 64.04000091552734,
      "word": "mani"
    },
    {
      "end": 66.0999984741211,
      "start": 65.0999984741211,
      "word": "e"
    },
    {
      "end": 66.69999694824219,
      "start": 66.0999984741211,
      "word": "le"
    },
    {
      "end": 67.37999725341797,
      "start": 66.69999694824219,
      "word": "tue"
    },
    {
      "end": 69.9800033569336,
      "start": 67.37999725341797,
      "word": "bocce"
    },
    {
      "end": 72.69999694824219,
      "start": 71.54000091552734,
      "word": "le"
    },
    {
      "end": 72.76000213623047,
      "start": 72.69999694824219,
      "word": "tue"
    },
    {
      "end": 76.45999908447266,
      "start": 72.76000213623047,
      "word": "bocce"
    },
    {
      "end": 80.4800033569336,
      "start": 76.55999755859375,
      "word": "le"
    },
    {
      "end": 80.4800033569336,
      "start": 80.4800033569336,
      "word": "tue"
    },
    {
      "end": 85.80000305175781,
      "start": 80.4800033569336,
      "word": "bocce"
    },
    {
      "end": 93.18000030517578,
      "start": 91.77999877929688,
      "word": "Batti"
    },
    {
      "end": 94.18000030517578,
      "start": 94.16000366210938,
      "word": "batti"
    },
    {
      "end": 94.5999984741211,
      "start": 94.5999984741211,
      "word": "o"
    },
    {
      "end": 95.4800033569336,
      "start": 94.5999984741211,
      "word": "bel"
    },
    {
      "end": 96.69999694824219,
      "start": 95.4800033569336,
      "word": "masecco"
    },
    {
      "end": 97.5,
      "start": 96.69999694824219,
      "word": "da"
    },
    {
      "end": 98.37999725341797,
      "start": 97.5,
      "word": "tua"
    },
    {
      "end": 100.5,
      "start": 98.37999725341797,
      "word": "povera"
    },
    {
      "end": 101.68000030517578,
      "start": 100.5,
      "word": "zerlina"
    },
    {
      "end": 103.4000015258789,
      "start": 102.91999816894531,
      "word": "star\u00f2"
    },
    {
      "end": 104.4000015258789,
      "start": 103.4000015258789,
      "word": "qui"
    },
    {
      "end": 104.87999725341797,
      "start": 104.45999908447266,
      "word": "com"
    },
    {
      "end": 105.41999816894531,
      "start": 104.87999725341797,
      "word": "un"
    },
    {
      "end": 106.91999816894531,
      "start": 105.41999816894531,
      "word": "gallina"
    },
    {
      "end": 108.13999938964844,
      "start": 108.08000183105469,
      "word": "le"
    },
    {
      "end": 108.69999694824219,
      "start": 108.13999938964844,
      "word": "tue"
    },
    {
      "end": 109.55999755859375,
      "start": 108.69999694824219,
      "word": "botte"
    },
    {
      "end": 110.68000030517578,
      "start": 109.55999755859375,
      "word": "ad"
    },
    {
      "end": 112.30000305175781,
      "start": 110.68000030517578,
      "word": "aspettar"
    },
    {
      "end": 115.27999877929688,
      "start": 113.87999725341797,
      "word": "Batti"
    },
    {
      "end": 115.27999877929688,
      "start": 115.27999877929688,
      "word": "batti"
    },
    {
      "end": 115.27999877929688,
      "start": 115.27999877929688,
      "word": "o"
    },
    {
      "end": 116.18000030517578,
      "start": 115.27999877929688,
      "word": "bel"
    },
    {
      "end": 118.23999786376953,
      "start": 116.18000030517578,
      "word": "masecco"
    },
    {
      "end": 121.31999969482422,
      "start": 118.23999786376953,
      "word": "da"
    },
    {
      "end": 121.72000122070312,
      "start": 121.31999969482422,
      "word": "tua"
    },
    {
      "end": 122.73999786376953,
      "start": 121.72000122070312,
      "word": "povera"
    },
    {
      "end": 122.73999786376953,
      "start": 122.73999786376953,
      "word": "zerlina"
    },
    {
      "end": 124.31999969482422,
      "start": 123.26000213623047,
      "word": "star\u00f2"
    },
    {
      "end": 125.37999725341797,
      "start": 124.31999969482422,
      "word": "qui"
    },
    {
      "end": 128.39999389648438,
      "start": 125.5999984741211,
      "word": "com"
    },
    {
      "end": 128.39999389648438,
      "start": 128.39999389648438,
      "word": "un"
    },
    {
      "end": 128.39999389648438,
      "start": 128.39999389648438,
      "word": "gallina"
    },
    {
      "end": 128.5,
      "start": 128.39999389648438,
      "word": "le"
    },
    {
      "end": 129.47999572753906,
      "start": 128.5,
      "word": "tue"
    },
    {
      "end": 130.3000030517578,
      "start": 129.47999572753906,
      "word": "botte"
    },
    {
      "end": 131.1199951171875,
      "start": 130.3000030517578,
      "word": "ad"
    },
    {
      "end": 133.22000122070312,
      "start": 131.1199951171875,
      "word": "aspettar"
    },
    {
      "end": 139.3800048828125,
      "start": 137.97999572753906,
      "word": "Anna"
    },
    {
      "end": 140.77999877929688,
      "start": 139.3800048828125,
      "word": "vedo"
    },
    {
      "end": 141.83999633789062,
      "start": 141.82000732421875,
      "word": "non"
    },
    {
      "end": 142.25999450683594,
      "start": 141.83999633789062,
      "word": "hai"
    },
    {
      "end": 143.5399932861328,
      "start": 142.25999450683594,
      "word": "cuore"
    },
    {
      "end": 149.52000427246094,
      "start": 148.1199951171875,
      "word": "Anna"
    },
    {
      "end": 150.9199981689453,
      "start": 149.52000427246094,
      "word": "vedo"
    },
    {
      "end": 155.4199981689453,
      "start": 151.82000732421875,
      "word": "non"
    },
    {
      "end": 155.4199981689453,
      "start": 155.4199981689453,
      "word": "hai"
    },
    {
      "end": 156.3800048828125,
      "start": 155.4199981689453,
      "word": "cuore"
    },
    {
      "end": 159.16000366210938,
      "start": 157.3800048828125,
      "word": "Pace"
    },
    {
      "end": 160.3800048828125,
      "start": 160.3800048828125,
      "word": "pace"
    },
    {
      "end": 161.25999450683594,
      "start": 160.5,
      "word": "oh"
    },
    {
      "end": 161.33999633789062,
      "start": 161.25999450683594,
      "word": "vita"
    },
    {
      "end": 166.36000061035156,
      "start": 161.33999633789062,
      "word": "mia"
    },
    {
      "end": 167.32000732421875,
      "start": 166.36000061035156,
      "word": "il"
    },
    {
      "end": 167.6999969482422,
      "start": 167.32000732421875,
      "word": "pi\u00f9"
    },
    {
      "end": 168.52000427246094,
      "start": 167.6999969482422,
      "word": "tendo"
    },
    {
      "end": 168.74000549316406,
      "start": 168.52000427246094,
      "word": "\u00e8"
    },
    {
      "end": 169.5,
      "start": 168.74000549316406,
      "word": "l"
    },
    {
      "end": 170.32000732421875,
      "start": 169.5,
      "word": "allegria"
    },
    {
      "end": 171.5800018310547,
      "start": 171.52000427246094,
      "word": "notte"
    },
    {
      "end": 172.4199981689453,
      "start": 171.5800018310547,
      "word": "di"
    },
    {
      "end": 173.0399932861328,
      "start": 172.4199981689453,
      "word": "voglia"
    },
    {
      "end": 178.24000549316406,
      "start": 173.0399932861328,
      "word": "passare"
    },
    {
      "end": 179.63999938964844,
      "start": 179.63999938964844,
      "word": "Notte"
    },
    {
      "end": 180.6199951171875,
      "start": 179.63999938964844,
      "word": "di"
    },
    {
      "end": 181.10000610351562,
      "start": 180.6199951171875,
      "word": "voglia"
    },
    {
      "end": 184.27999877929688,
      "start": 181.10000610351562,
      "word": "passare"
    },
    {
      "end": 185.55999755859375,
      "start": 184.8800048828125,
      "word": "notte"
    },
    {
      "end": 186.83999633789062,
      "start": 185.55999755859375,
      "word": "di"
    },
    {
      "end": 187.24000549316406,
      "start": 186.83999633789062,
      "word": "voglia"
    },
    {
      "end": 189.6999969482422,
      "start": 187.24000549316406,
      "word": "passare"
    },
    {
      "end": 191.67999267578125,
      "start": 190.86000061035156,
      "word": "notte"
    },
    {
      "end": 193.1999969482422,
      "start": 191.67999267578125,
      "word": "di"
    },
    {
      "end": 193.24000549316406,
      "start": 193.1999969482422,
      "word": "voglia"
    },
    {
      "end": 194.47999572753906,
      "start": 193.24000549316406,
      "word": "passare"
    },
    {
      "end": 195.60000610351562,
      "start": 194.47999572753906,
      "word": "Pace"
    },
    {
      "end": 196.63999938964844,
      "start": 196.63999938964844,
      "word": "pace"
    },
    {
      "end": 197.44000244140625,
      "start": 196.8000030517578,
      "word": "oh"
    },
    {
      "end": 197.55999755859375,
      "start": 197.44000244140625,
      "word": "vita"
    },
    {
      "end": 202.44000244140625,
      "start": 197.55999755859375,
      "word": "mia"
    },
    {
      "end": 203.44000244140625,
      "start": 202.5800018310547,
      "word": "il"
    },
    {
      "end": 204.1999969482422,
      "start": 203.44000244140625,
      "word": "pi\u00f9"
    },
    {
      "end": 204.36000061035156,
      "start": 204.1999969482422,
      "word": "tendo"
    },
    {
      "end": 204.72000122070312,
      "start": 204.36000061035156,
      "word": "\u00e8"
    },
    {
      "end": 205.1199951171875,
      "start": 204.72000122070312,
      "word": "l"
    },
    {
      "end": 206.4600067138672,
      "start": 205.1199951171875,
      "word": "allegria"
    },
    {
      "end": 207.67999267578125,
      "start": 207.5,
      "word": "notte"
    },
    {
      "end": 208.5399932861328,
      "start": 207.67999267578125,
      "word": "di"
    },
    {
      "end": 209.1999969482422,
      "start": 208.5399932861328,
      "word": "voglia"
    },
    {
      "end": 209.66000366210938,
      "start": 209.1999969482422,
      "word": "passare"
    },
    {
      "end": 210.36000061035156,
      "start": 210.0800018310547,
      "word": "Si"
    },
    {
      "end": 210.82000732421875,
      "start": 210.36000061035156,
      "word": "si"
    },
    {
      "end": 212.1999969482422,
      "start": 212.1999969482422,
      "word": "si"
    },
    {
      "end": 212.24000549316406,
      "start": 212.1999969482422,
      "word": "si"
    },
    {
      "end": 212.72000122070312,
      "start": 212.66000366210938,
      "word": "si"
    },
    {
      "end": 213.4600067138672,
      "start": 212.72000122070312,
      "word": "notte"
    },
    {
      "end": 214.39999389648438,
      "start": 213.4600067138672,
      "word": "di"
    },
    {
      "end": 214.86000061035156,
      "start": 214.39999389648438,
      "word": "voglia"
    },
    {
      "end": 215.75999450683594,
      "start": 214.86000061035156,
      "word": "passare"
    },
    {
      "end": 216.24000549316406,
      "start": 216.02000427246094,
      "word": "Si"
    },
    {
      "end": 216.47999572753906,
      "start": 216.27999877929688,
      "word": "si"
    },
    {
      "end": 217.13999938964844,
      "start": 216.9600067138672,
      "word": "si"
    },
    {
      "end": 217.5,
      "start": 217.24000549316406,
      "word": "si"
    },
    {
      "end": 218.39999389648438,
      "start": 217.67999267578125,
      "word": "si"
    },
    {
      "end": 219.3000030517578,
      "start": 218.8800048828125,
      "word": "notte"
    },
    {
      "end": 220.8000030517578,
      "start": 219.3000030517578,
      "word": "di"
    },
    {
      "end": 220.8000030517578,
      "start": 220.8000030517578,
      "word": "voglia"
    },
    {
      "end": 221.86000061035156,
      "start": 220.8000030517578,
      "word": "passare"
    },
    {
      "end": 223.8000030517578,
      "start": 222.86000061035156,
      "word": "Notte"
    },
    {
      "end": 223.82000732421875,
      "start": 223.8000030517578,
      "word": "di"
    },
    {
      "end": 223.86000061035156,
      "start": 223.82000732421875,
      "word": "voglia"
    },
    {
      "end": 226.83999633789062,
      "start": 223.86000061035156,
      "word": "passare"
    },
    {
      "end": 227.47999572753906,
      "start": 226.8800048828125,
      "word": "notte"
    },
    {
      "end": 227.47999572753906,
      "start": 227.47999572753906,
      "word": "di"
    },
    {
      "end": 227.75999450683594,
      "start": 227.47999572753906,
      "word": "voglia"
    },
    {
      "end": 231.0,
      "start": 227.75999450683594,
      "word": "passare"
    }
  ],
  "task": "transcribe"
}