{
  "duration": 135.11000061035156,
  "language": "italian",
  "text": "Ieri, senza vita, ho da sola in segreto la missione. Una nuova mia vita posso tutt'ora e nuova arriver\u00f2. Luzio Ponto non sa, dei miei non sanno. Lo Signor mio distaller\u00e0 in piena nubilit\u00e0. Ma il mio del Signor finch\u00e8 non tocca in piena Il mio destino \u00e8 la stessa risetta. In Gioia noi vedremo la stessa vita. E per farvi contenta potr\u00f2 un'ansia mia, Ma il mio del Signor finch\u00e8 non tocca in piena Amore mio!",
  "words": [
    {
      "end": 2.059999942779541,
      "start": 0.0,
      "word": "Ieri"
    },
    {
      "end": 3.700000047683716,
      "start": 2.740000009536743,
      "word": "senza"
    },
    {
      "end": 5.659999847412109,
      "start": 3.700000047683716,
      "word": "vita"
    },
    {
      "end": 6.739999771118164,
      "start": 6.340000152587891,
      "word": "ho"
    },
    {
      "end": 7.039999961853027,
      "start": 6.739999771118164,
      "word": "da"
    },
    {
      "end": 7.980000019073486,
      "start": 7.039999961853027,
      "word": "sola"
    },
    {
      "end": 8.420000076293945,
      "start": 7.980000019073486,
      "word": "in"
    },
    {
      "end": 9.420000076293945,
      "start": 8.420000076293945,
      "word": "segreto"
    },
    {
      "end": 10.300000190734863,
      "start": 9.420000076293945,
      "word": "la"
    },
    {
      "end": 14.0,
      "start": 10.300000190734863,
      "word": "missione"
    },
    {
      "end": 15.640000343322754,
      "start": 14.0,
      "word": "Una"
    },
    {
      "end": 16.799999237060547,
      "start": 15.640000343322754,
      "word": "nuova"
    },
    {
      "end": 17.760000228881836,
      "start": 16.799999237060547,
      "word": "mia"
    },
    {
      "end": 19.100000381469727,
      "start": 17.760000228881836,
      "word": "vita"
    },
    {
      "end": 20.440000534057617,
      "start": 19.100000381469727,
      "word": "posso"
    },
    {
      "end": 21.440000534057617,
      "start": 20.440000534057617,
      "word": "tutt"
    },
    {
      "end": 22.799999237060547,
      "start": 21.440000534057617,
      "word": "ora"
    },
    {
      "end": 23.700000762939453,
      "start": 22.799999237060547,
      "word": "e"
    },
    {
      "end": 24.34000015258789,
      "start": 23.700000762939453,
      "word": "nuova"
    },
    {
      "end": 28.68000030517578,
      "start": 24.34000015258789,
      "word": "arriver\u00f2"
    },
    {
      "end": 33.560001373291016,
      "start": 32.15999984741211,
      "word": "Luzio"
    },
    {
      "end": 34.29999923706055,
      "start": 33.560001373291016,
      "word": "Ponto"
    },
    {
      "end": 35.34000015258789,
      "start": 34.29999923706055,
      "word": "non"
    },
    {
      "end": 35.34000015258789,
      "start": 35.34000015258789,
      "word": "sa"
    },
    {
      "end": 36.52000045776367,
      "start": 35.939998626708984,
      "word": "dei"
    },
    {
      "end": 36.880001068115234,
      "start": 36.52000045776367,
      "word": "miei"
    },
    {
      "end": 37.619998931884766,
      "start": 36.880001068115234,
      "word": "non"
    },
    {
      "end": 39.439998626708984,
      "start": 37.619998931884766,
      "word": "sanno"
    },
    {
      "end": 43.900001525878906,
      "start": 42.5,
      "word": "Lo"
    },
    {
      "end": 45.29999923706055,
      "start": 43.900001525878906,
      "word": "Signor"
    },
    {
      "end": 46.459999084472656,
      "start": 45.29999923706055,
      "word": "mio"
    },
    {
      "end": 51.560001373291016,
      "start": 46.459999084472656,
      "word": "distaller\u00e0"
    },
    {
      "end": 53.119998931884766,
      "start": 51.560001373291016,
      "word": "in"
    },
    {
      "end": 54.91999816894531,
      "start": 53.119998931884766,
      "word": "piena"
    },
    {
      "end": 58.939998626708984,
      "start": 54.91999816894531,
      "word": "nubilit\u00e0"
    },
    {
      "end": 60.619998931884766,
      "start": 58.939998626708984,
      "word": "Ma"
    },
    {
      "end": 60.900001525878906,
      "start": 60.619998931884766,
      "word": "il"
    },
    {
      "end": 61.380001068115234,
      "start": 60.900001525878906,
      "word": "mio"
    },
    {
      "end": 61.880001068115234,
      "start": 61.380001068115234,
      "word": "del"
    },
    {
      "end": 62.58000183105469,
      "start": 61.880001068115234,
      "word": "Signor"
    },
    {
      "end": 63.540000915527344,
      "start": 62.58000183105469,
      "word": "finch\u00e8"
    },
    {
      "end": 63.779998779296875,
      "start": 63.540000915527344,
      "word": "non"
    },
    {
      "end": 64.33999633789062,
      "start": 63.779998779296875,
      "word": "tocca"
    },
    {
      "end": 65.08000183105469,
      "start": 64.33999633789062,
      "word": "in"
    },
    {
      "end": 65.94000244140625,
      "start": 65.08000183105469,
      "word": "piena"
    },
    {
      "end": 68.37999725341797,
      "start": 66.94000244140625,
      "word": "Il"
    },
    {
      "end": 69.27999877929688,
      "start": 68.37999725341797,
      "word": "mio"
    },
    {
      "end": 71.31999969482422,
      "start": 69.27999877929688,
      "word": "destino"
    },
    {
      "end": 73.44000244140625,
      "start": 71.31999969482422,
      "word": "\u00e8"
    },
    {
      "end": 74.36000061035156,
      "start": 73.44000244140625,
      "word": "la"
    },
    {
      "end": 76.19999694824219,
      "start": 74.36000061035156,
      "word": "stessa"
    },
    {
      "end": 79.27999877929688,
      "start": 76.19999694824219,
      "word": "risetta"
    },
    {
      "end": 80.91999816894531,
      "start": 79.27999877929688,
      "word": "In"
    },
    {
      "end": 83.69999694824219,
      "start": 80.91999816894531,
      "word": "Gioia"
    },
    {
      "end": 86.83999633789062,
      "start": 83.69999694824219,
      "word": "noi"
    },
    {
      "end": 89.9000015258789,
      "start": 86.83999633789062,
      "word": "vedremo"
    },
    {
      "end": 92.0199966430664,
      "start": 89.9000015258789,
      "word": "la"
    },
    {
      "end": 92.54000091552734,
      "start": 92.0199966430664,
      "word": "stessa"
    },
    {
      "end": 94.31999969482422,
      "start": 92.54000091552734,
      "word": "vita"
    },
    {
      "end": 98.66000366210938,
      "start": 97.26000213623047,
      "word": "E"
    },
    {
      "end": 99.22000122070312,
      "start": 98.66000366210938,
      "word": "per"
    },
    {
      "end": 100.73999786376953,
      "start": 99.22000122070312,
      "word": "farvi"
    },
    {
      "end": 102.76000213623047,
      "start": 100.73999786376953,
      "word": "contenta"
    },
    {
      "end": 105.5999984741211,
      "start": 102.76000213623047,
      "word": "potr\u00f2"
    },
    {
      "end": 106.69999694824219,
      "start": 105.5999984741211,
      "word": "un"
    },
    {
      "end": 107.66000366210938,
      "start": 106.69999694824219,
      "word": "ansia"
    },
    {
      "end": 108.36000061035156,
      "start": 107.66000366210938,
      "word": "mia"
    },
    {
      "end": 109.44000244140625,
      "start": 108.36000061035156,
      "word": "Ma"
    },
    {
      "end": 110.30000305175781,
      "start": 109.44000244140625,
      "word": "il"
    },
    {
      "end": 110.30000305175781,
      "start": 110.30000305175781,
      "word": "mio"
    },
    {
      "end": 112.4000015258789,
      "start": 110.30000305175781,
      "word": "del"
    },
    {
      "end": 112.66000366210938,
      "start": 112.4000015258789,
      "word": "Signor"
    },
    {
      "end": 112.66000366210938,
      "start": 112.66000366210938,
      "word": "finch\u00e8"
    },
    {
      "end": 112.66000366210938,
      "start": 112.66000366210938,
      "word": "non"
    },
    {
      "end": 112.66000366210938,
      "start": 112.66000366210938,
      "word": "tocca"
    },
    {
      "end": 112.66000366210938,
      "start": 112.66000366210938,
      "word": "in"
    },
    {
      "end": 112.66000366210938,
      "start": 112.66000366210938,
      "word": "piena"
    },
    {
      "end": 133.66000366210938,
      "start": 132.25999450683594,
      "word": "Amore"
    },
    {
      "end": 135.05999755859375,
      "start": 133.66000366210938,
      "word": "mio"
    }
  ],
  "task": "transcribe"
}