{
  "duration": 147.1199951171875,
  "language": "italian",
  "text": "Chi l'ha richiesto? Vediamo. Nara, fuori dal naro. Colline, Rotolfe, tu Marcello. Siamo lasciuto. Oh merda, ho trenta soldi in tutta. Come? Non c'\u00e8 pi\u00f9? Ma il mio tesoro per... Non vi occorre. Date a mano. E spazzolate con quello e con questo. Marcello, Marcello. Eh, signor! S\u00ec, signor! E d\u00e0mi il signor, e d\u00e0mi il signor, e d\u00e0mi il signor. E d\u00e0mi il senso ed ubito, e d\u00e0mi il suo saluto. E d\u00e0mi il senso ed ubito, e d\u00e0mi il suo saluto. Nara, fuori dal naro. Colline, Rotolfe, tu Marcello. E fuori dal naro. E' un'altra terra che nella famiglia Belli. E' una pagione. Gi\u00f9 c'\u00e8 un tampicone. E' una pagione. E' una pagione. Besti, besti, besti. L\u00ec non c'\u00e8 una realt\u00e0. E' una pagione. E' una pagione. E' una pagione. Sottotitoli creati dalla comunit\u00e0 Amara.org",
  "segments": null,
  "words": [
    {
      "end": 1.059999942779541,
      "start": 0.0,
      "word": "Chi"
    },
    {
      "end": 1.1399999856948853,
      "start": 1.059999942779541,
      "word": "l"
    },
    {
      "end": 1.1399999856948853,
      "start": 1.1399999856948853,
      "word": "ha"
    },
    {
      "end": 2.4000000953674316,
      "start": 1.1399999856948853,
      "word": "richiesto"
    },
    {
      "end": 7.420000076293945,
      "start": 6.639999866485596,
      "word": "Vediamo"
    },
    {
      "end": 11.739999771118164,
      "start": 10.960000038146973,
      "word": "Nara"
    },
    {
      "end": 13.600000381469727,
      "start": 13.579999923706055,
      "word": "fuori"
    },
    {
      "end": 13.800000190734863,
      "start": 13.600000381469727,
      "word": "dal"
    },
    {
      "end": 14.260000228881836,
      "start": 13.800000190734863,
      "word": "naro"
    },
    {
      "end": 15.579999923706055,
      "start": 15.220000267028809,
      "word": "Colline"
    },
    {
      "end": 16.579999923706055,
      "start": 16.219999313354492,
      "word": "Rotolfe"
    },
    {
      "end": 16.979999542236328,
      "start": 16.780000686645508,
      "word": "tu"
    },
    {
      "end": 17.3700008392334,
      "start": 16.979999542236328,
      "word": "Marcello"
    },
    {
      "end": 18.0,
      "start": 18.0,
      "word": "Siamo"
    },
    {
      "end": 18.739999771118164,
      "start": 18.0,
      "word": "lasciuto"
    },
    {
      "end": 20.079999923706055,
      "start": 19.520000457763672,
      "word": "Oh"
    },
    {
      "end": 20.079999923706055,
      "start": 20.079999923706055,
      "word": "merda"
    },
    {
      "end": 20.440000534057617,
      "start": 20.260000228881836,
      "word": "ho"
    },
    {
      "end": 20.860000610351562,
      "start": 20.440000534057617,
      "word": "trenta"
    },
    {
      "end": 21.18000030517578,
      "start": 20.860000610351562,
      "word": "soldi"
    },
    {
      "end": 21.459999084472656,
      "start": 21.18000030517578,
      "word": "in"
    },
    {
      "end": 21.559999465942383,
      "start": 21.459999084472656,
      "word": "tutta"
    },
    {
      "end": 22.739999771118164,
      "start": 22.040000915527344,
      "word": "Come"
    },
    {
      "end": 23.200000762939453,
      "start": 23.15999984741211,
      "word": "Non"
    },
    {
      "end": 23.34000015258789,
      "start": 23.200000762939453,
      "word": "c"
    },
    {
      "end": 23.34000015258789,
      "start": 23.34000015258789,
      "word": "\u00e8"
    },
    {
      "end": 23.68000030517578,
      "start": 23.34000015258789,
      "word": "pi\u00f9"
    },
    {
      "end": 24.280000686645508,
      "start": 24.100000381469727,
      "word": "Ma"
    },
    {
      "end": 24.399999618530273,
      "start": 24.280000686645508,
      "word": "il"
    },
    {
      "end": 24.739999771118164,
      "start": 24.399999618530273,
      "word": "mio"
    },
    {
      "end": 25.739999771118164,
      "start": 24.739999771118164,
      "word": "tesoro"
    },
    {
      "end": 27.3799991607666,
      "start": 25.739999771118164,
      "word": "per"
    },
    {
      "end": 32.52000045776367,
      "start": 31.200000762939453,
      "word": "Non"
    },
    {
      "end": 32.79999923706055,
      "start": 32.52000045776367,
      "word": "vi"
    },
    {
      "end": 33.560001373291016,
      "start": 32.79999923706055,
      "word": "occorre"
    },
    {
      "end": 34.220001220703125,
      "start": 34.220001220703125,
      "word": "Date"
    },
    {
      "end": 34.34000015258789,
      "start": 34.220001220703125,
      "word": "a"
    },
    {
      "end": 35.0,
      "start": 34.34000015258789,
      "word": "mano"
    },
    {
      "end": 45.86000061035156,
      "start": 44.540000915527344,
      "word": "E"
    },
    {
      "end": 46.400001525878906,
      "start": 45.86000061035156,
      "word": "spazzolate"
    },
    {
      "end": 46.7599983215332,
      "start": 46.400001525878906,
      "word": "con"
    },
    {
      "end": 46.880001068115234,
      "start": 46.7599983215332,
      "word": "quello"
    },
    {
      "end": 47.13999938964844,
      "start": 46.880001068115234,
      "word": "e"
    },
    {
      "end": 47.41999816894531,
      "start": 47.13999938964844,
      "word": "con"
    },
    {
      "end": 48.08000183105469,
      "start": 47.41999816894531,
      "word": "questo"
    },
    {
      "end": 51.47999954223633,
      "start": 50.68000030517578,
      "word": "Marcello"
    },
    {
      "end": 52.380001068115234,
      "start": 51.720001220703125,
      "word": "Marcello"
    },
    {
      "end": 53.47999954223633,
      "start": 52.380001068115234,
      "word": "Eh"
    },
    {
      "end": 53.880001068115234,
      "start": 53.47999954223633,
      "word": "signor"
    },
    {
      "end": 54.47999954223633,
      "start": 54.08000183105469,
      "word": "S\u00ec"
    },
    {
      "end": 55.040000915527344,
      "start": 54.47999954223633,
      "word": "signor"
    },
    {
      "end": 58.2599983215332,
      "start": 57.29999923706055,
      "word": "E"
    },
    {
      "end": 58.34000015258789,
      "start": 58.2599983215332,
      "word": "d\u00e0mi"
    },
    {
      "end": 58.380001068115234,
      "start": 58.34000015258789,
      "word": "il"
    },
    {
      "end": 59.040000915527344,
      "start": 58.380001068115234,
      "word": "signor"
    },
    {
      "end": 59.7400016784668,
      "start": 59.040000915527344,
      "word": "e"
    },
    {
      "end": 59.7400016784668,
      "start": 59.7400016784668,
      "word": "d\u00e0mi"
    },
    {
      "end": 59.7599983215332,
      "start": 59.7400016784668,
      "word": "il"
    },
    {
      "end": 60.279998779296875,
      "start": 59.7599983215332,
      "word": "signor"
    },
    {
      "end": 61.959999084472656,
      "start": 60.279998779296875,
      "word": "e"
    },
    {
      "end": 62.459999084472656,
      "start": 61.959999084472656,
      "word": "d\u00e0mi"
    },
    {
      "end": 62.459999084472656,
      "start": 62.459999084472656,
      "word": "il"
    },
    {
      "end": 62.459999084472656,
      "start": 62.459999084472656,
      "word": "signor"
    },
    {
      "end": 63.02000045776367,
      "start": 62.5,
      "word": "E"
    },
    {
      "end": 64.0199966430664,
      "start": 63.02000045776367,
      "word": "d\u00e0mi"
    },
    {
      "end": 64.23999786376953,
      "start": 64.0199966430664,
      "word": "il"
    },
    {
      "end": 64.36000061035156,
      "start": 64.23999786376953,
      "word": "senso"
    },
    {
      "end": 64.77999877929688,
      "start": 64.36000061035156,
      "word": "ed"
    },
    {
      "end": 65.81999969482422,
      "start": 64.77999877929688,
      "word": "ubito"
    },
    {
      "end": 65.83999633789062,
      "start": 65.81999969482422,
      "word": "e"
    },
    {
      "end": 66.4800033569336,
      "start": 65.83999633789062,
      "word": "d\u00e0mi"
    },
    {
      "end": 66.95999908447266,
      "start": 66.4800033569336,
      "word": "il"
    },
    {
      "end": 67.22000122070312,
      "start": 66.95999908447266,
      "word": "suo"
    },
    {
      "end": 67.69999694824219,
      "start": 67.22000122070312,
      "word": "saluto"
    },
    {
      "end": 69.18000030517578,
      "start": 69.18000030517578,
      "word": "E"
    },
    {
      "end": 70.04000091552734,
      "start": 69.18000030517578,
      "word": "d\u00e0mi"
    },
    {
      "end": 70.31999969482422,
      "start": 70.04000091552734,
      "word": "il"
    },
    {
      "end": 70.54000091552734,
      "start": 70.31999969482422,
      "word": "senso"
    },
    {
      "end": 72.0,
      "start": 70.54000091552734,
      "word": "ed"
    },
    {
      "end": 72.0199966430664,
      "start": 72.0,
      "word": "ubito"
    },
    {
      "end": 72.76000213623047,
      "start": 72.0199966430664,
      "word": "e"
    },
    {
      "end": 72.76000213623047,
      "start": 72.76000213623047,
      "word": "d\u00e0mi"
    },
    {
      "end": 72.81999969482422,
      "start": 72.76000213623047,
      "word": "il"
    },
    {
      "end": 73.0,
      "start": 72.81999969482422,
      "word": "suo"
    },
    {
      "end": 74.37999725341797,
      "start": 73.0,
      "word": "saluto"
    },
    {
      "end": 75.76000213623047,
      "start": 75.27999877929688,
      "word": "Nara"
    },
    {
      "end": 76.55999755859375,
      "start": 75.77999877929688,
      "word": "fuori"
    },
    {
      "end": 76.87999725341797,
      "start": 76.55999755859375,
      "word": "dal"
    },
    {
      "end": 77.0199966430664,
      "start": 76.87999725341797,
      "word": "naro"
    },
    {
      "end": 77.5,
      "start": 77.5,
      "word": "Colline"
    },
    {
      "end": 78.19999694824219,
      "start": 77.5,
      "word": "Rotolfe"
    },
    {
      "end": 79.45999908447266,
      "start": 78.19999694824219,
      "word": "tu"
    },
    {
      "end": 79.95999908447266,
      "start": 79.45999908447266,
      "word": "Marcello"
    },
    {
      "end": 80.0199966430664,
      "start": 79.95999908447266,
      "word": "E"
    },
    {
      "end": 80.91999816894531,
      "start": 80.0199966430664,
      "word": "fuori"
    },
    {
      "end": 81.73999786376953,
      "start": 80.91999816894531,
      "word": "dal"
    },
    {
      "end": 81.73999786376953,
      "start": 81.73999786376953,
      "word": "naro"
    },
    {
      "end": 81.73999786376953,
      "start": 81.73999786376953,
      "word": "E"
    },
    {
      "end": 81.73999786376953,
      "start": 81.73999786376953,
      "word": "un"
    },
    {
      "end": 81.73999786376953,
      "start": 81.73999786376953,
      "word": "altra"
    },
    {
      "end": 81.73999786376953,
      "start": 81.73999786376953,
      "word": "terra"
    },
    {
      "end": 83.26000213623047,
      "start": 81.73999786376953,
      "word": "che"
    },
    {
      "end": 83.5999984741211,
      "start": 83.26000213623047,
      "word": "nella"
    },
    {
      "end": 84.0999984741211,
      "start": 83.5999984741211,
      "word": "famiglia"
    },
    {
      "end": 84.73999786376953,
      "start": 84.0999984741211,
      "word": "Belli"
    },
    {
      "end": 86.41999816894531,
      "start": 86.19999694824219,
      "word": "E"
    },
    {
      "end": 86.68000030517578,
      "start": 86.54000091552734,
      "word": "una"
    },
    {
      "end": 87.9000015258789,
      "start": 86.68000030517578,
      "word": "pagione"
    },
    {
      "end": 89.41999816894531,
      "start": 88.9000015258789,
      "word": "Gi\u00f9"
    },
    {
      "end": 89.86000061035156,
      "start": 89.41999816894531,
      "word": "c"
    },
    {
      "end": 89.86000061035156,
      "start": 89.86000061035156,
      "word": "\u00e8"
    },
    {
      "end": 90.23999786376953,
      "start": 89.86000061035156,
      "word": "un"
    },
    {
      "end": 90.76000213623047,
      "start": 90.23999786376953,
      "word": "tampicone"
    },
    {
      "end": 91.81999969482422,
      "start": 91.81999969482422,
      "word": "E"
    },
    {
      "end": 92.08000183105469,
      "start": 91.81999969482422,
      "word": "una"
    },
    {
      "end": 92.66000366210938,
      "start": 92.08000183105469,
      "word": "pagione"
    },
    {
      "end": 93.31999969482422,
      "start": 93.31999969482422,
      "word": "E"
    },
    {
      "end": 93.31999969482422,
      "start": 93.31999969482422,
      "word": "una"
    },
    {
      "end": 93.37999725341797,
      "start": 93.31999969482422,
      "word": "pagione"
    },
    {
      "end": 94.69999694824219,
      "start": 93.66000366210938,
      "word": "Besti"
    },
    {
      "end": 94.76000213623047,
      "start": 94.76000213623047,
      "word": "besti"
    },
    {
      "end": 94.83999633789062,
      "start": 94.83999633789062,
      "word": "besti"
    },
    {
      "end": 95.87999725341797,
      "start": 95.45999908447266,
      "word": "L\u00ec"
    },
    {
      "end": 96.4000015258789,
      "start": 95.87999725341797,
      "word": "non"
    },
    {
      "end": 96.81999969482422,
      "start": 96.4000015258789,
      "word": "c"
    },
    {
      "end": 96.81999969482422,
      "start": 96.81999969482422,
      "word": "\u00e8"
    },
    {
      "end": 97.18000030517578,
      "start": 96.81999969482422,
      "word": "una"
    },
    {
      "end": 97.80000305175781,
      "start": 97.18000030517578,
      "word": "realt\u00e0"
    },
    {
      "end": 98.80000305175781,
      "start": 98.69999694824219,
      "word": "E"
    },
    {
      "end": 98.9800033569336,
      "start": 98.80000305175781,
      "word": "una"
    },
    {
      "end": 100.36000061035156,
      "start": 98.9800033569336,
      "word": "pagione"
    },
    {
      "end": 102.33999633789062,
      "start": 102.18000030517578,
      "word": "E"
    },
    {
      "end": 102.80000305175781,
      "start": 102.4000015258789,
      "word": "una"
    },
    {
      "end": 103.33999633789062,
      "start": 102.80000305175781,
      "word": "pagione"
    },
    {
      "end": 107.76000213623047,
      "start": 106.72000122070312,
      "word": "E"
    },
    {
      "end": 108.45999908447266,
      "start": 107.77999877929688,
      "word": "una"
    },
    {
      "end": 109.22000122070312,
      "start": 108.45999908447266,
      "word": "pagione"
    },
    {
      "end": 147.0399932861328,
      "start": 147.0,
      "word": "Sottotitoli"
    },
    {
      "end": 147.05999755859375,
      "start": 147.0399932861328,
      "word": "creati"
    },
    {
      "end": 147.05999755859375,
      "start": 147.05999755859375,
      "word": "dalla"
    },
    {
      "end": 147.05999755859375,
      "start": 147.05999755859375,
      "word": "comunit\u00e0"
    },
    {
      "end": 147.0800018310547,
      "start": 147.05999755859375,
      "word": "Amara"
    },
    {
      "end": 147.10000610351562,
      "start": 147.0800018310547,
      "word": "org"
    }
  ],
  "task": "transcribe"
}